src/EX_Stage/ALU/alu.v
`timescale 1ns / 1ps

// Define a module called "ALU"
module ALU(DATA1, DATA2, RESULT, SELECT, EQUAL, SIGNEDLT, UNSIGNEDLT);
    
    // Inputs and Outputs
    input[31:0] DATA1, DATA2;   // defining variables to get the input values
    input[4:0] SELECT;          // variable to store the ALU opcode
    output reg[31:0] RESULT;    // variable to store the result of the ALU
    output EQUAL, SIGNEDLT, UNSIGNEDLT; // defining output signals

    // defining variables to store the results of each airthmatic operation
    wire[31:0]  AND_RES,    // and operation
                OR_RES,     // or operation
                XOR_RES,    // xor operation 
                ADD_RES,    // addition operation
                SUB_RES,    // subtraction
                SLL_RES,    // shift left logical
                SRL_RES,    // shift right logical
                SRA_RES,    // shift right airthmatic
                FWD_RES,    // forward operation
                MUL_RES,    // multiplication
                MULH_RES,   // multiplication higher signed * signed
                MULHU_RES,  // multiplication higher unsigned * unsigned
                MULHSU_RES, // multiplication higher signed * unsigned
                DIV_RES,    // division
                DIVU_RES,       // unsigned division
                REM_RES,    // signed remainder
                REMU_RES,    // unsigned remainder
                SLT_RES,    // less than
                SLTU_RES;   // less than unsigned

    wire [63:0] MULTIPICATION; 

    // operating bitwise operations with 3 time unit delay

    //R type instructions
    assign  #1 AND_RES = DATA1 & DATA2;
    assign  #1 OR_RES = DATA1 | DATA2;
    assign  #1 XOR_RES = DATA1 ^ DATA2;
    assign  #2 ADD_RES = DATA1 + DATA2;
    assign  #2 SUB_RES = DATA1 - DATA2;

    // forwading operation
    assign  #3 FWD_RES = DATA2;
    

    // shift operations (use only lower 5 bits of shift amount)
    assign  #1 SLL_RES = DATA1 << DATA2[4:0];
    assign  #1 SRL_RES = DATA1 >> DATA2[4:0];
    assign  #1 SRA_RES = $signed(DATA1) >>> DATA2[4:0];

    // multipication operation
    assign  #3 MUL_RES = DATA1 * DATA2;
    
    // High multiplication operations - return upper 32 bits
    assign MULTIPICATION = $signed(DATA1) * $signed(DATA2);
    assign  #3 MULH_RES = MULTIPICATION[63:32];
    
    // For unsigned multiplication, we need to properly handle the 64-bit result
    wire [63:0] MULHU_TEMP = DATA1 * DATA2;
    assign  #3 MULHU_RES = MULHU_TEMP[63:32];
    
    // For signed * unsigned, cast appropriately
    wire signed [63:0] MULHSU_TEMP = $signed(DATA1) * {1'b0, DATA2};
    assign  #3 MULHSU_RES = MULHSU_TEMP[63:32];

    // division operation
    assign  #3 DIV_RES = $signed(DATA1) / $signed(DATA2);
    assign  #3 DIVU_RES = $unsigned(DATA1) / $unsigned(DATA2);


    // remainder operations
    assign  #3 REM_RES = $signed(DATA1) % $signed(DATA2);
    assign  #3 REMU_RES = $unsigned(DATA1) % $unsigned(DATA2);

    // set the output value according to the comparison of DATA1 and DATA2
    assign  #1 SLT_RES = ($signed(DATA1) < $signed(DATA2)) ? 32'd1 : 32'd0;
    assign  #1 SLTU_RES = ($unsigned(DATA1) < $unsigned(DATA2)) ? 32'd1 : 32'd0;


    always@(*)
    begin
        case(SELECT)
        5'b00000: RESULT = FWD_RES;  
        5'b00001: RESULT = ADD_RES; 
        5'b00010: RESULT = SUB_RES; 
        5'b00011: RESULT = SLL_RES;
        5'b00100: RESULT = SLT_RES;
        5'b00101: RESULT = SLTU_RES;
        5'b00110: RESULT = XOR_RES;
        5'b00111: RESULT = SRL_RES;
        5'b01000: RESULT = SRA_RES;
        5'b01001: RESULT = OR_RES;
        5'b01010: RESULT = AND_RES;
        5'b01011: RESULT = MUL_RES;
        5'b01100: RESULT = MULH_RES;
        5'b01101: RESULT = MULHSU_RES;
        5'b01110: RESULT = MULHU_RES;
        5'b01111: RESULT = DIV_RES;
        5'b10000: RESULT = DIVU_RES;
        5'b10001: RESULT = REM_RES;
        5'b10010: RESULT = REMU_RES;
        default:RESULT = 31'd0;
    endcase
    end

    assign EQUAL = ~(|RESULT);      // DATA1 == DATA2
    assign SIGNEDLT = RESULT[31];   // DATA1 < DATA2
    assign UNSIGNEDLT= SLTU_RES[0]; // |DATA1| < |DATA2|

endmodule

src/EX_Stage/ALU/alu_tb.v
`timescale 1ns/1ps

module alu_tb();
    // Testbench signals
    reg [31:0] DATA1, DATA2;
    reg [4:0] SELECT;
    wire [31:0] RESULT;
    wire EQUAL, SIGNEDLT, UNSIGNEDLT;
    
    // Test variables
    integer i;
    reg [31:0] expected_result;
    
    // Instantiate the ALU module
    ALU dut (
        .DATA1(DATA1),
        .DATA2(DATA2),
        .RESULT(RESULT),
        .SELECT(SELECT),
        .EQUAL(EQUAL),
        .SIGNEDLT(SIGNEDLT),
        .UNSIGNEDLT(UNSIGNEDLT)
    );
    
    // Task to display test results
    task display_result;
        input [4:0] op_code;
        input [31:0] data1, data2;
        input [31:0] expected;
        input [79:0] operation_name; // 10 characters max
        begin
            #10; // Wait for ALU to compute
            $display("Time: %0t | Op: %s | DATA1: %h | DATA2: %h | RESULT: %h | Expected: %h | EQUAL: %b | SIGNEDLT: %b | UNSIGNEDLT: %b", 
                     $time, operation_name, data1, data2, RESULT, expected, EQUAL, SIGNEDLT, UNSIGNEDLT);
            
            if (RESULT !== expected) begin
                $display("ERROR: Expected %h, got %h", expected, RESULT);
            end
        end
    endtask
    
    // Task to test an operation
    task test_operation;
        input [4:0] op_code;
        input [31:0] data1, data2;
        input [31:0] expected;
        input [79:0] operation_name;
        begin
            DATA1 = data1;
            DATA2 = data2;
            SELECT = op_code;
            display_result(op_code, data1, data2, expected, operation_name);
        end
    endtask
    
    initial begin
        $display("=== ALU Testbench Started ===");
        $display("Time | Operation | DATA1    | DATA2    | RESULT   | Expected | EQ | SLT | ULT");
        $display("-----|-----------|----------|----------|----------|----------|----|----|----");
        
        // Initialize inputs
        DATA1 = 0;
        DATA2 = 0;
        SELECT = 0;
        #5;
        
        // Test 1: Forward operation (FWD_RES)
        test_operation(5'b00000, 32'h12345678, 32'hABCDEF00, 32'hABCDEF00, "FWD");
        
        // Test 2: Addition (ADD_RES)
        test_operation(5'b00001, 32'h00000010, 32'h00000020, 32'h00000030, "ADD");
        test_operation(5'b00001, 32'hFFFFFFFF, 32'h00000001, 32'h00000000, "ADD_OVF");
        
        // Test 3: Subtraction (SUB_RES)
        test_operation(5'b00010, 32'h00000020, 32'h00000010, 32'h00000010, "SUB");
        test_operation(5'b00010, 32'h00000010, 32'h00000020, 32'hFFFFFFF0, "SUB_NEG");
        
        // Test 4: Shift Left Logical (SLL_RES)
        test_operation(5'b00011, 32'h00000001, 32'h00000004, 32'h00000010, "SLL");
        test_operation(5'b00011, 32'hF0F0F0F0, 32'h00000002, 32'hC3C3C3C0, "SLL2");
        
        // Test 5: Set Less Than (SLT_RES)
        test_operation(5'b00100, 32'h00000010, 32'h00000020, 32'h00000001, "SLT_T");
        test_operation(5'b00100, 32'h00000020, 32'h00000010, 32'h00000000, "SLT_F");
        test_operation(5'b00100, 32'hFFFFFFF0, 32'h00000010, 32'h00000001, "SLT_NEG");
        
        // Test 6: Set Less Than Unsigned (SLTU_RES)
        test_operation(5'b00101, 32'h00000010, 32'h00000020, 32'h00000001, "SLTU_T");
        test_operation(5'b00101, 32'hFFFFFFF0, 32'h00000010, 32'h00000000, "SLTU_F");
        
        // Test 7: XOR (XOR_RES)
        test_operation(5'b00110, 32'hF0F0F0F0, 32'h0F0F0F0F, 32'hFFFFFFFF, "XOR");
        test_operation(5'b00110, 32'hAAAAAAAA, 32'hAAAAAAAA, 32'h00000000, "XOR_SAME");
        
        // Test 8: Shift Right Logical (SRL_RES)
        test_operation(5'b00111, 32'h80000000, 32'h00000004, 32'h08000000, "SRL");
        test_operation(5'b00111, 32'hF0F0F0F0, 32'h00000002, 32'h3C3C3C3C, "SRL2");
        
        // Test 9: Shift Right Arithmetic (SRA_RES)
        test_operation(5'b01000, 32'h80000000, 32'h00000004, 32'hF8000000, "SRA");
        test_operation(5'b01000, 32'h7FFFFFFF, 32'h00000004, 32'h07FFFFFF, "SRA_POS");
        
        // Test 10: OR (OR_RES)
        test_operation(5'b01001, 32'hF0F0F0F0, 32'h0F0F0F0F, 32'hFFFFFFFF, "OR");
        test_operation(5'b01001, 32'h00000000, 32'hFFFFFFFF, 32'hFFFFFFFF, "OR_ALL");
        
        // Test 11: AND (AND_RES)
        test_operation(5'b01010, 32'hF0F0F0F0, 32'h0F0F0F0F, 32'h00000000, "AND");
        test_operation(5'b01010, 32'hFFFFFFFF, 32'hAAAAAAAA, 32'hAAAAAAAA, "AND_MASK");
        
        // Test 12: Multiplication (MUL_RES)
        test_operation(5'b01011, 32'h00000010, 32'h00000020, 32'h00000200, "MUL");
        test_operation(5'b01011, 32'hFFFFFFFF, 32'h00000002, 32'hFFFFFFFE, "MUL_NEG");
        
        // Test 13: Multiplication High Signed (MULH_RES)
        test_operation(5'b01100, 32'h80000000, 32'h80000000, 32'h40000000, "MULH");
        
        // Test 14: Multiplication High Signed*Unsigned (MULHSU_RES)
        test_operation(5'b01101, 32'hFFFFFFFF, 32'h80000000, 32'h7FFFFFFF, "MULHSU");
        
        // Test 15: Multiplication High Unsigned (MULHU_RES)
        test_operation(5'b01110, 32'hFFFFFFFF, 32'hFFFFFFFF, 32'hFFFFFFFE, "MULHU");
        
        // Test 16: Division (DIV_RES)
        test_operation(5'b01111, 32'h00000100, 32'h00000010, 32'h00000010, "DIV");
        test_operation(5'b01111, 32'hFFFFFFF0, 32'h00000002, 32'hFFFFFFF8, "DIV_NEG");
        
        // Test 17: Division Unsigned (DIVU_RES)
        test_operation(5'b10000, 32'hFFFFFFF0, 32'h00000002, 32'h7FFFFFF8, "DIVU");
        
        // Test 18: Remainder (REM_RES)
        test_operation(5'b10001, 32'h00000017, 32'h00000005, 32'h00000003, "REM");
        test_operation(5'b10001, 32'hFFFFFFF9, 32'h00000005, 32'hFFFFFFFE, "REM_NEG");
        
        // Test 19: Remainder Unsigned (REMU_RES)
        test_operation(5'b10010, 32'h00000017, 32'h00000005, 32'h00000003, "REMU");
        
        // Test 20: Default case
        test_operation(5'b11111, 32'h12345678, 32'hABCDEF00, 32'h00000000, "DEFAULT");
        
        // Special tests for flag outputs
        $display("\n=== Testing Flag Outputs ===");
        
        // Test EQUAL flag
        DATA1 = 32'h12345678;
        DATA2 = 32'h12345678;
        SELECT = 5'b00010; // SUB operation should give 0
        #10;
        $display("EQUAL test (same values): DATA1=%h, DATA2=%h, RESULT=%h, EQUAL=%b (should be 1)", 
                 DATA1, DATA2, RESULT, EQUAL);
        
        // Test SIGNEDLT flag
        DATA1 = 32'hFFFFFFF0; // -16 in signed
        DATA2 = 32'h00000010; // +16
        SELECT = 5'b00010; // SUB operation
        #10;
        $display("SIGNEDLT test (negative result): DATA1=%h, DATA2=%h, RESULT=%h, SIGNEDLT=%b (should be 1)", 
                 DATA1, DATA2, RESULT, SIGNEDLT);
        
        // Test UNSIGNEDLT flag
        DATA1 = 32'h00000010;
        DATA2 = 32'h00000020;
        SELECT = 5'b00101; // SLTU operation
        #10;
        $display("UNSIGNEDLT test: DATA1=%h, DATA2=%h, RESULT=%h, UNSIGNEDLT=%b (should be 1)", 
                 DATA1, DATA2, RESULT, UNSIGNEDLT);
        
        $display("\n=== ALU Testbench Completed ===");
        $finish;
    end
    
    // Generate VCD file for waveform viewing
    initial begin
        $dumpfile("alu_tb.vcd");
        $dumpvars(0, alu_tb);
    end
    
endmodule

src/EX_Stage/ALU/alu_tb.vcd
$date
	Thu Jul 10 15:23:34 2025
$end
$version
	Icarus Verilog
$end
$timescale
	1ps
$end
$scope module alu_tb $end
$var wire 1 ! UNSIGNEDLT $end
$var wire 1 " SIGNEDLT $end
$var wire 32 # RESULT [31:0] $end
$var wire 1 $ EQUAL $end
$var reg 32 % DATA1 [31:0] $end
$var reg 32 & DATA2 [31:0] $end
$var reg 5 ' SELECT [4:0] $end
$scope module dut $end
$var wire 32 ( AND_RES [31:0] $end
$var wire 32 ) DATA1 [31:0] $end
$var wire 32 * DATA2 [31:0] $end
$var wire 1 $ EQUAL $end
$var wire 32 + FWD_RES [31:0] $end
$var wire 32 , OR_RES [31:0] $end
$var wire 5 - SELECT [4:0] $end
$var wire 32 . XOR_RES [31:0] $end
$var wire 1 ! UNSIGNEDLT $end
$var wire 32 / SUB_RES [31:0] $end
$var wire 32 0 SRL_RES [31:0] $end
$var wire 32 1 SRA_RES [31:0] $end
$var wire 32 2 SLT_RES [31:0] $end
$var wire 32 3 SLTU_RES [31:0] $end
$var wire 32 4 SLL_RES [31:0] $end
$var wire 1 " SIGNEDLT $end
$var wire 32 5 REM_RES [31:0] $end
$var wire 32 6 REMU_RES [31:0] $end
$var wire 32 7 MUL_RES [31:0] $end
$var wire 64 8 MULTIPICATION [63:0] $end
$var wire 32 9 MULH_RES [31:0] $end
$var wire 64 : MULHU_TEMP [63:0] $end
$var wire 32 ; MULHU_RES [31:0] $end
$var wire 64 < MULHSU_TEMP [63:0] $end
$var wire 32 = MULHSU_RES [31:0] $end
$var wire 32 > DIV_RES [31:0] $end
$var wire 32 ? DIVU_RES [31:0] $end
$var wire 32 @ ADD_RES [31:0] $end
$var reg 32 A RESULT [31:0] $end
$upscope $end
$scope task display_result $end
$var reg 32 B data1 [31:0] $end
$var reg 32 C data2 [31:0] $end
$var reg 32 D expected [31:0] $end
$var reg 5 E op_code [4:0] $end
$var reg 80 F operation_name [79:0] $end
$upscope $end
$scope task test_operation $end
$var reg 32 G data1 [31:0] $end
$var reg 32 H data2 [31:0] $end
$var reg 32 I expected [31:0] $end
$var reg 5 J op_code [4:0] $end
$var reg 80 K operation_name [79:0] $end
$upscope $end
$upscope $end
$enddefinitions $end
$comment Show the parameter values. $end
$dumpall
$end
#0
$dumpvars
bx K
bx J
bx I
bx H
bx G
bx F
bx E
bx D
bx C
bx B
bx A
bx @
bx ?
bx >
bx =
b0 <
bx ;
b0 :
bx 9
b0 8
bx 7
bx 6
bx 5
bx 4
bx 3
bx 2
bx 1
bx 0
bx /
bx .
b0 -
bx ,
bx +
b0 *
b0 )
bx (
b0 '
b0 &
b0 %
x$
bx #
x"
x!
$end
#1000
0!
b0 4
b0 0
b0 1
b0 .
b0 ,
b0 (
b0 2
b0 3
#2000
b0 @
b0 /
#3000
1$
0"
b0 #
b0 A
b0 9
b0 ;
b0 =
b0 +
b0 7
#5000
b10001100101011101000100 F
b10101011110011011110111100000000 D
b10101011110011011110111100000000 C
b10010001101000101011001111000 B
b0 E
b1111101000000011010001000011001001000010110100100000100000000000 8
b110000110111100110101010101001000010110100100000100000000000 :
b110000110111100110101010101001000010110100100000100000000000 <
b10101011110011011110111100000000 &
b10101011110011011110111100000000 *
b10010001101000101011001111000 %
b10010001101000101011001111000 )
b10001100101011101000100 K
b10101011110011011110111100000000 I
b10101011110011011110111100000000 H
b10010001101000101011001111000 G
b0 J
#6000
1!
b1 3
b10000001000100011000000000 (
b10111011111111011111111101111000 ,
b10111001111110011011100101111000 .
b10010001101000101011001111000 4
b10010001101000101011001111000 0
b10010001101000101011001111000 1
#7000
b10111110000000100100010101111000 @
b1100110011001100110011101111000 /
#8000
0$
1"
b10101011110011011110111100000000 #
b10101011110011011110111100000000 A
b11111010000000110100010000110010 9
b1100001101111001101010101010 ;
b1100001101111001101010101010 =
b10101011110011011110111100000000 +
b1000010110100100000100000000000 7
b0 >
b0 ?
b10010001101000101011001111000 5
b10010001101000101011001111000 6
#15000
b10111110000000100100010101111000 #
b10111110000000100100010101111000 A
b10000010100010001000100 F
b110000 D
b100000 C
b10000 B
b1 E
b1 '
b1 -
b100000 &
b100000 *
b1000000000 8
b1000000000 :
b1000000000 <
b10000 %
b10000 )
b10000010100010001000100 K
b110000 I
b100000 H
b10000 G
b1 J
#16000
b1 2
b0 (
b110000 ,
b110000 .
b10000 4
b10000 0
b10000 1
#17000
0"
b110000 #
b110000 A
b110000 @
b11111111111111111111111111110000 /
#18000
b0 9
b0 ;
b0 =
b100000 +
b1000000000 7
b10000 5
b10000 6
#25000
b1000001010001000100010001011111010011110101011001000110 F
b0 D
b1 C
b11111111111111111111111111111111 B
b1 &
b1 *
b1111111111111111111111111111111111111111111111111111111111111111 8
b11111111111111111111111111111111 :
b11111111111111111111111111111111 <
b11111111111111111111111111111111 %
b11111111111111111111111111111111 )
b1000001010001000100010001011111010011110101011001000110 K
b0 I
b1 H
b11111111111111111111111111111111 G
#26000
0!
b1 (
b11111111111111111111111111111111 ,
b11111111111111111111111111111110 .
b0 3
b11111111111111111111111111111110 4
b1111111111111111111111111111111 0
b11111111111111111111111111111111 1
#27000
1$
b0 #
b0 A
b0 @
b11111111111111111111111111111110 /
#28000
b11111111111111111111111111111111 9
b1 +
b11111111111111111111111111111111 >
b11111111111111111111111111111111 7
b11111111111111111111111111111111 ?
b0 5
b0 6
#35000
0$
1"
b11111111111111111111111111111110 #
b11111111111111111111111111111110 A
b10100110101010101000010 F
b10000 D
b10000 C
b100000 B
b10 E
b10 '
b10 -
b10000 &
b10000 *
b1000000000 8
b1000000000 :
b1000000000 <
b100000 %
b100000 )
b10100110101010101000010 K
b10000 I
b10000 H
b100000 G
b10 J
#36000
b0 (
b110000 ,
b110000 .
b0 2
b1000000000000000000000 4
b0 0
b0 1
#37000
0"
b10000 #
b10000 A
b110000 @
b10000 /
#38000
b0 9
b10000 +
b1000000000 7
b10 >
b10 ?
#45000
b1010011010101010100001001011111010011100100010101000111 F
b11111111111111111111111111110000 D
b100000 C
b10000 B
b100000 &
b100000 *
b1000000000 8
b1000000000 :
b1000000000 <
b10000 %
b10000 )
b1010011010101010100001001011111010011100100010101000111 K
b11111111111111111111111111110000 I
b100000 H
b10000 G
#46000
1!
b10000 0
b10000 1
b1 2
b1 3
b10000 4
#47000
1"
b11111111111111111111111111110000 #
b11111111111111111111111111110000 A
b11111111111111111111111111110000 /
#48000
b100000 +
b10000 5
b10000 6
b0 >
b0 ?
#55000
0"
b10000 #
b10000 A
b10100110100110001001100 F
b10000 D
b100 C
b1 B
b11 E
b11 '
b11 -
b100 &
b100 *
b100 8
b100 :
b100 <
b1 %
b1 )
b10100110100110001001100 K
b10000 I
b100 H
b1 G
b11 J
#56000
b101 ,
b101 .
b0 0
b0 1
#57000
b101 @
b11111111111111111111111111111101 /
#58000
b100 +
b100 7
b1 5
b1 6
#65000
b1010011010011000100110000110010 F
b11000011110000111100001111000000 D
b10 C
b11110000111100001111000011110000 B
b10 &
b10 *
b1111111111111111111111111111111111100001111000011110000111100000 8
b111100001111000011110000111100000 :
b111100001111000011110000111100000 <
b11110000111100001111000011110000 %
b11110000111100001111000011110000 )
b1010011010011000100110000110010 K
b11000011110000111100001111000000 I
b10 H
b11110000111100001111000011110000 G
#66000
1"
0!
b11000011110000111100001111000000 #
b11000011110000111100001111000000 A
b11110000111100001111000011110010 ,
b11110000111100001111000011110010 .
b0 3
b11000011110000111100001111000000 4
b111100001111000011110000111100 0
b11111100001111000011110000111100 1
#67000
b11110000111100001111000011110010 @
b11110000111100001111000011101110 /
#68000
b11111111111111111111111111111111 9
b1 ;
b1 =
b10 +
b11100001111000011110000111100000 7
b11111000011110000111100001111000 >
b1111000011110000111100001111000 ?
b0 5
b0 6
#75000
0"
b1 #
b1 A
b101001101001100010101000101111101010100 F
b1 D
b100000 C
b10000 B
b100 E
b100 '
b100 -
b100000 &
b100000 *
b1000000000 8
b1000000000 :
b1000000000 <
b10000 %
b10000 )
b101001101001100010101000101111101010100 K
b1 I
b100000 H
b10000 G
b100 J
#76000
1!
b1 3
b110000 ,
b110000 .
b10000 4
b10000 0
b10000 1
#77000
b110000 @
b11111111111111111111111111110000 /
#78000
b0 9
b0 ;
b0 =
b100000 +
b10000 5
b10000 6
b1000000000 7
b0 >
b0 ?
#85000
b101001101001100010101000101111101000110 F
b0 D
b10000 C
b100000 B
b10000 &
b10000 *
b1000000000 8
b1000000000 :
b1000000000 <
b100000 %
b100000 )
b101001101001100010101000101111101000110 K
b0 I
b10000 H
b100000 G
#86000
1$
0!
b0 #
b0 A
b0 2
b0 3
b1000000000000000000000 4
b0 0
b0 1
#87000
b10000 /
#88000
b10000 +
b10 >
b10 ?
b0 5
b0 6
#95000
b1010011010011000101010001011111010011100100010101000111 F
b1 D
b11111111111111111111111111110000 B
b1111111111111111111111111111111111111111111111111111111100000000 8
b111111111111111111111111111100000000 :
b111111111111111111111111111100000000 <
b11111111111111111111111111110000 %
b11111111111111111111111111110000 )
b1010011010011000101010001011111010011100100010101000111 K
b1 I
b11111111111111111111111111110000 G
#96000
0$
b1 #
b1 A
b10000 (
b11111111111111111111111111110000 ,
b11111111111111111111111111100000 .
b1 2
b11111111111100000000000000000000 4
b1111111111111111 0
b11111111111111111111111111111111 1
#97000
b0 @
b11111111111111111111111111100000 /
#98000
b11111111111111111111111111111111 9
b1111 ;
b1111 =
b11111111111111111111111100000000 7
b11111111111111111111111111111111 >
b1111111111111111111111111111 ?
#105000
1$
b0 #
b0 A
b10100110100110001010100010101010101111101010100 F
b100000 C
b10000 B
b101 E
b101 '
b101 -
b100000 &
b100000 *
b1000000000 8
b1000000000 :
b1000000000 <
b10000 %
b10000 )
b10100110100110001010100010101010101111101010100 K
b100000 H
b10000 G
b101 J
#106000
0$
1!
b1 #
b1 A
b1 3
b0 (
b110000 ,
b110000 .
b10000 4
b10000 0
b10000 1
#107000
b110000 @
b11111111111111111111111111110000 /
#108000
b0 9
b0 ;
b0 =
b100000 +
b10000 5
b10000 6
b1000000000 7
b0 >
b0 ?
#115000
b10100110100110001010100010101010101111101000110 F
b0 D
b10000 C
b11111111111111111111111111110000 B
b10000 &
b10000 *
b1111111111111111111111111111111111111111111111111111111100000000 8
b111111111111111111111111111100000000 :
b111111111111111111111111111100000000 <
b11111111111111111111111111110000 %
b11111111111111111111111111110000 )
b10100110100110001010100010101010101111101000110 K
b0 I
b10000 H
b11111111111111111111111111110000 G
#116000
1$
0!
b0 #
b0 A
b10000 (
b11111111111111111111111111110000 ,
b11111111111111111111111111100000 .
b0 3
b11111111111100000000000000000000 4
b1111111111111111 0
b11111111111111111111111111111111 1
#117000
b0 @
b11111111111111111111111111100000 /
#118000
b11111111111111111111111111111111 9
b1111 ;
b1111 =
b10000 +
b11111111111111111111111111111111 >
b0 6
b11111111111111111111111100000000 7
b1111111111111111111111111111 ?
b0 5
#125000
0$
1"
b11111111111111111111111111100000 #
b11111111111111111111111111100000 A
b10110000100111101010010 F
b11111111111111111111111111111111 D
b1111000011110000111100001111 C
b11110000111100001111000011110000 B
b110 E
b110 '
b110 -
b1111000011110000111100001111 &
b1111000011110000111100001111 *
b1111111100011101001110110101100101101010010011000010111000010000 8
b111000101100010010100110100001101010010011000010111000010000 :
b111000101100010010100110100001101010010011000010111000010000 <
b11110000111100001111000011110000 %
b11110000111100001111000011110000 )
b10110000100111101010010 K
b11111111111111111111111111111111 I
b1111000011110000111100001111 H
b11110000111100001111000011110000 G
b110 J
#126000
b11111111111111111111111111111111 #
b11111111111111111111111111111111 A
b0 (
b11111111111111111111111111111111 ,
b11111111111111111111111111111111 .
b1111000011110000000000000000000 4
b11110000111100001 0
b11111111111111111110000111100001 1
#127000
b11111111111111111111111111111111 @
b11100001111000011110000111100001 /
#128000
b11111111000111010011101101011001 9
b1110001011000100101001101000 ;
b1110001011000100101001101000 =
b1111000011110000111100001111 +
b11111111111111111111111111111111 5
b1101010010011000010111000010000 7
b10000 ?
#135000
b101100001001111010100100101111101010011010000010100110101000101 F
b0 D
b10101010101010101010101010101010 C
b10101010101010101010101010101010 B
b10101010101010101010101010101010 &
b10101010101010101010101010101010 *
b1110001110001110001110001110011100011100011100011100011100100 8
b111000111000111000111000111000011100011100011100011100011100100 :
b111000111000111000111000111000011100011100011100011100011100100 <
b10101010101010101010101010101010 %
b10101010101010101010101010101010 )
b101100001001111010100100101111101010011010000010100110101000101 K
b0 I
b10101010101010101010101010101010 H
b10101010101010101010101010101010 G
#136000
1$
0"
b0 #
b0 A
b0 2
b10101010101010101010101010101010 (
b10101010101010101010101010101010 ,
b0 .
b10101010101010101010100000000000 4
b1010101010101010101010 0
b11111111111010101010101010101010 1
#137000
b1010101010101010101010101010100 @
b0 /
#138000
b11100011100011100011100011100 9
b1110001110001110001110001110000 ;
b1110001110001110001110001110000 =
b10101010101010101010101010101010 +
b11100011100011100011100011100100 7
b1 >
b1 ?
b0 5
#145000
0$
b1010101010101010101010 #
b1010101010101010101010 A
b10100110101001001001100 F
b1000000000000000000000000000 D
b100 C
b10000000000000000000000000000000 B
b111 E
b111 '
b111 -
b100 &
b100 *
b1111111111111111111111111111111000000000000000000000000000000000 8
b1000000000000000000000000000000000 :
b1000000000000000000000000000000000 <
b10000000000000000000000000000000 %
b10000000000000000000000000000000 )
b10100110101001001001100 K
b1000000000000000000000000000 I
b100 H
b10000000000000000000000000000000 G
b111 J
#146000
b1000000000000000000000000000 #
b1000000000000000000000000000 A
b0 (
b10000000000000000000000000000100 ,
b10000000000000000000000000000100 .
b1 2
b0 4
b1000000000000000000000000000 0
b11111000000000000000000000000000 1
#147000
b10000000000000000000000000000100 @
b1111111111111111111111111111100 /
#148000
b11111111111111111111111111111110 9
b10 ;
b10 =
b100 +
b11100000000000000000000000000000 >
b0 7
b100000000000000000000000000000 ?
#155000
b1010011010100100100110000110010 F
b111100001111000011110000111100 D
b10 C
b11110000111100001111000011110000 B
b10 &
b10 *
b1111111111111111111111111111111111100001111000011110000111100000 8
b111100001111000011110000111100000 :
b111100001111000011110000111100000 <
b11110000111100001111000011110000 %
b11110000111100001111000011110000 )
b1010011010100100100110000110010 K
b111100001111000011110000111100 I
b10 H
b11110000111100001111000011110000 G
#156000
b111100001111000011110000111100 #
b111100001111000011110000111100 A
b11110000111100001111000011110010 ,
b11110000111100001111000011110010 .
b11000011110000111100001111000000 4
b111100001111000011110000111100 0
b11111100001111000011110000111100 1
#157000
b11110000111100001111000011110010 @
b11110000111100001111000011101110 /
#158000
b11111111111111111111111111111111 9
b1 ;
b1 =
b10 +
b11100001111000011110000111100000 7
b11111000011110000111100001111000 >
b1111000011110000111100001111000 ?
#165000
1"
b11111100001111000011110000111100 #
b11111100001111000011110000111100 A
b10100110101001001000001 F
b11111000000000000000000000000000 D
b100 C
b10000000000000000000000000000000 B
b1000 E
b1000 '
b1000 -
b100 &
b100 *
b1111111111111111111111111111111000000000000000000000000000000000 8
b1000000000000000000000000000000000 :
b1000000000000000000000000000000000 <
b10000000000000000000000000000000 %
b10000000000000000000000000000000 )
b10100110101001001000001 K
b11111000000000000000000000000000 I
b100 H
b10000000000000000000000000000000 G
b1000 J
#166000
b11111000000000000000000000000000 #
b11111000000000000000000000000000 A
b10000000000000000000000000000100 ,
b10000000000000000000000000000100 .
b0 4
b1000000000000000000000000000 0
b11111000000000000000000000000000 1
#167000
b10000000000000000000000000000100 @
b1111111111111111111111111111100 /
#168000
b11111111111111111111111111111110 9
b10 ;
b10 =
b100 +
b0 7
b11100000000000000000000000000000 >
b100000000000000000000000000000 ?
#175000
b1010011010100100100000101011111010100000100111101010011 F
b111111111111111111111111111 D
b1111111111111111111111111111111 B
b111111111111111111111111111111100 8
b111111111111111111111111111111100 :
b111111111111111111111111111111100 <
b1111111111111111111111111111111 %
b1111111111111111111111111111111 )
b1010011010100100100000101011111010100000100111101010011 K
b111111111111111111111111111 I
b1111111111111111111111111111111 G
#176000
0"
b111111111111111111111111111 #
b111111111111111111111111111 A
b100 (
b1111111111111111111111111111111 ,
b1111111111111111111111111111011 .
b0 2
b11111111111111111111111111110000 4
b111111111111111111111111111 0
b111111111111111111111111111 1
#177000
b10000000000000000000000000000011 @
b1111111111111111111111111111011 /
#178000
b1 9
b1 ;
b1 =
b11111111111111111111111111111100 7
b11111111111111111111111111111 >
b11111111111111111111111111111 ?
b11 5
b11 6
#185000
b1111111111111111111111111111111 #
b1111111111111111111111111111111 A
b100111101010010 F
b11111111111111111111111111111111 D
b1111000011110000111100001111 C
b11110000111100001111000011110000 B
b1001 E
b1001 '
b1001 -
b1111000011110000111100001111 &
b1111000011110000111100001111 *
b1111111100011101001110110101100101101010010011000010111000010000 8
b111000101100010010100110100001101010010011000010111000010000 :
b111000101100010010100110100001101010010011000010111000010000 <
b11110000111100001111000011110000 %
b11110000111100001111000011110000 )
b100111101010010 K
b11111111111111111111111111111111 I
b1111000011110000111100001111 H
b11110000111100001111000011110000 G
b1001 J
#186000
1"
b11111111111111111111111111111111 #
b11111111111111111111111111111111 A
b0 (
b11111111111111111111111111111111 ,
b11111111111111111111111111111111 .
b1 2
b1111000011110000000000000000000 4
b11110000111100001 0
b11111111111111111110000111100001 1
#187000
b11111111111111111111111111111111 @
b11100001111000011110000111100001 /
#188000
b11111111000111010011101101011001 9
b1110001011000100101001101000 ;
b1110001011000100101001101000 =
b1111000011110000111100001111 +
b1101010010011000010111000010000 7
b11111111111111111111111111111111 >
b10000 ?
b11111111111111111111111111111111 5
b0 6
#195000
b10011110101001001011111010000010100110001001100 F
b11111111111111111111111111111111 C
b0 B
b11111111111111111111111111111111 &
b11111111111111111111111111111111 *
b0 8
b0 :
b0 <
b0 %
b0 )
b10011110101001001011111010000010100110001001100 K
b11111111111111111111111111111111 H
b0 G
#196000
1!
b0 2
b1 3
b0 4
b0 0
b0 1
#197000
b1 /
#198000
b0 9
b0 ;
b0 =
b11111111111111111111111111111111 +
b0 7
b0 >
b0 ?
b0 5
