src/EX_Stage/ALU/alu.v
`timescale 1ns / 1ps

// Define a module called "ALU"
module ALU(DATA1, DATA2, RESULT, SELECT);
    
    // Inputs and Outputs
    input[31:0] DATA1, DATA2;   // defining variables to get the input values
    input[4:0] SELECT;          // variable to store the ALU opcode
    output reg[31:0] RESULT;    // variable to store the result of the ALU

    // defining variables to store the results of each airthmatic operation
    wire[31:0]  AND_RES,    // and operation
                OR_RES,     // or operation
                XOR_RES,    // xor operation 
                ADD_RES,    // addition operation
                SUB_RES,    // subtraction
                SLL_RES,    // shift left logical
                SRL_RES,    // shift right logical
                SRA_RES,    // shift right airthmatic
                FWD_RES,    // forward operation
                MUL_RES,    // multiplication
                MULH_RES,   // multiplication higher signed * signed
                MULHU_RES,  // multiplication higher unsigned * unsigned
                MULHSU_RES, // multiplication higher signed * unsigned
                DIV_RES,    // division
                DIVU_RES,       // unsigned division
                REM_RES,    // signed remainder
                REMU_RES,    // unsigned remainder
                SLT_RES,    // less than
                SLTU_RES;   // less than unsigned

    wire [63:0] MULTIPICATION; 

    // operating bitwise operations with 3 time unit delay

    //R type instructions
    assign  #1 AND_RES = DATA1 & DATA2;
    assign  #1 OR_RES = DATA1 | DATA2;
    assign  #1 XOR_RES = DATA1 ^ DATA2;
    assign  #2 ADD_RES = DATA1 + DATA2;
    assign  #2 SUB_RES = DATA1 - DATA2;

    // forwading operation
    assign  #3 FWD_RES = DATA2;
    

    // shift operations (use only lower 5 bits of shift amount)
    assign  #1 SLL_RES = DATA1 << DATA2[4:0];
    assign  #1 SRL_RES = DATA1 >> DATA2[4:0];
    assign  #1 SRA_RES = $signed(DATA1) >>> DATA2[4:0];

    // multipication operation
    assign  #3 MUL_RES = DATA1 * DATA2;
    
    // High multiplication operations - return upper 32 bits
    assign MULTIPICATION = $signed(DATA1) * $signed(DATA2);
    assign  #3 MULH_RES = MULTIPICATION[63:32];
    
    // For unsigned multiplication, we need to properly handle the 64-bit result
    wire [63:0] MULHU_TEMP = DATA1 * DATA2;
    assign  #3 MULHU_RES = MULHU_TEMP[63:32];
    
    // For signed * unsigned, cast appropriately
    wire signed [63:0] MULHSU_TEMP = $signed(DATA1) * {1'b0, DATA2};
    assign  #3 MULHSU_RES = MULHSU_TEMP[63:32];

    // division operation
    assign  #3 DIV_RES = $signed(DATA1) / $signed(DATA2);
    assign  #3 DIVU_RES = $unsigned(DATA1) / $unsigned(DATA2);


    // remainder operations
    assign  #3 REM_RES = $signed(DATA1) % $signed(DATA2);
    assign  #3 REMU_RES = $unsigned(DATA1) % $unsigned(DATA2);

    // set the output value according to the comparison of DATA1 and DATA2
    assign  #1 SLT_RES = ($signed(DATA1) < $signed(DATA2)) ? 32'd1 : 32'd0;
    assign  #1 SLTU_RES = ($unsigned(DATA1) < $unsigned(DATA2)) ? 32'd1 : 32'd0;


    always@(*)
    begin
        case(SELECT)
        5'b00000: RESULT = FWD_RES;  
        5'b00001: RESULT = ADD_RES; 
        5'b00010: RESULT = SUB_RES; 
        5'b00011: RESULT = SLL_RES;
        5'b00100: RESULT = SLT_RES;
        5'b00101: RESULT = SLTU_RES;
        5'b00110: RESULT = XOR_RES;
        5'b00111: RESULT = SRL_RES;
        5'b01000: RESULT = SRA_RES;
        5'b01001: RESULT = OR_RES;
        5'b01010: RESULT = AND_RES;
        5'b01011: RESULT = MUL_RES;
        5'b01100: RESULT = MULH_RES;
        5'b01101: RESULT = MULHSU_RES;
        5'b01110: RESULT = MULHU_RES;
        5'b01111: RESULT = DIV_RES;
        5'b10000: RESULT = DIVU_RES;
        5'b10001: RESULT = REM_RES;
        5'b10010: RESULT = REMU_RES;
        default:RESULT = 31'd0;
    endcase
    end

endmodule

src/EX_Stage/ALU/alu_tb.v
`timescale 1ns/1ps

module alu_tb();
    // Testbench signals
    reg [31:0] DATA1, DATA2;
    reg [4:0] SELECT;
    wire [31:0] RESULT;
    
    // Test variables
    integer i;
    reg [31:0] expected_result;
    
    // Instantiate the ALU module
    ALU dut (
        .DATA1(DATA1),
        .DATA2(DATA2),
        .RESULT(RESULT),
        .SELECT(SELECT)
    );
    
    // Task to display test results
    task display_result;
        input [4:0] op_code;
        input [31:0] data1, data2;
        input [31:0] expected;
        input [79:0] operation_name; // 10 characters max
        begin
            #10; // Wait for ALU to compute
            $display("Time: %0t | Op: %s | DATA1: %h | DATA2: %h | RESULT: %h | Expected: %h", 
                     $time, operation_name, data1, data2, RESULT, expected);
            
            if (RESULT !== expected) begin
                $display("ERROR: Expected %h, got %h", expected, RESULT);
            end
        end
    endtask
    
    // Task to test an operation
    task test_operation;
        input [4:0] op_code;
        input [31:0] data1, data2;
        input [31:0] expected;
        input [79:0] operation_name;
        begin
            DATA1 = data1;
            DATA2 = data2;
            SELECT = op_code;
            display_result(op_code, data1, data2, expected, operation_name);
        end
    endtask
    
    initial begin
        $display("=== ALU Testbench Started ===");
        $display("Time | Operation | DATA1    | DATA2    | RESULT   | Expected |");
        $display("-----|-----------|----------|----------|----------|----------|");
        
        // Initialize inputs
        DATA1 = 0;
        DATA2 = 0;
        SELECT = 0;
        #5;
        
        // Test 1: Forward operation (FWD_RES)
        test_operation(5'b00000, 32'h12345678, 32'hABCDEF00, 32'hABCDEF00, "FWD");
        
        // Test 2: Addition (ADD_RES)
        test_operation(5'b00001, 32'h00000010, 32'h00000020, 32'h00000030, "ADD");
        test_operation(5'b00001, 32'hFFFFFFFF, 32'h00000001, 32'h00000000, "ADD_OVF");
        
        // Test 3: Subtraction (SUB_RES)
        test_operation(5'b00010, 32'h00000020, 32'h00000010, 32'h00000010, "SUB");
        test_operation(5'b00010, 32'h00000010, 32'h00000020, 32'hFFFFFFF0, "SUB_NEG");
        
        // Test 4: Shift Left Logical (SLL_RES)
        test_operation(5'b00011, 32'h00000001, 32'h00000004, 32'h00000010, "SLL");
        test_operation(5'b00011, 32'hF0F0F0F0, 32'h00000002, 32'hC3C3C3C0, "SLL2");
        
        // Test 5: Set Less Than (SLT_RES)
        test_operation(5'b00100, 32'h00000010, 32'h00000020, 32'h00000001, "SLT_T");
        test_operation(5'b00100, 32'h00000020, 32'h00000010, 32'h00000000, "SLT_F");
        test_operation(5'b00100, 32'hFFFFFFF0, 32'h00000010, 32'h00000001, "SLT_NEG");
        
        // Test 6: Set Less Than Unsigned (SLTU_RES)
        test_operation(5'b00101, 32'h00000010, 32'h00000020, 32'h00000001, "SLTU_T");
        test_operation(5'b00101, 32'hFFFFFFF0, 32'h00000010, 32'h00000000, "SLTU_F");
        
        // Test 7: XOR (XOR_RES)
        test_operation(5'b00110, 32'hF0F0F0F0, 32'h0F0F0F0F, 32'hFFFFFFFF, "XOR");
        test_operation(5'b00110, 32'hAAAAAAAA, 32'hAAAAAAAA, 32'h00000000, "XOR_SAME");
        
        // Test 8: Shift Right Logical (SRL_RES)
        test_operation(5'b00111, 32'h80000000, 32'h00000004, 32'h08000000, "SRL");
        test_operation(5'b00111, 32'hF0F0F0F0, 32'h00000002, 32'h3C3C3C3C, "SRL2");
        
        // Test 9: Shift Right Arithmetic (SRA_RES)
        test_operation(5'b01000, 32'h80000000, 32'h00000004, 32'hF8000000, "SRA");
        test_operation(5'b01000, 32'h7FFFFFFF, 32'h00000004, 32'h07FFFFFF, "SRA_POS");
        
        // Test 10: OR (OR_RES)
        test_operation(5'b01001, 32'hF0F0F0F0, 32'h0F0F0F0F, 32'hFFFFFFFF, "OR");
        test_operation(5'b01001, 32'h00000000, 32'hFFFFFFFF, 32'hFFFFFFFF, "OR_ALL");
        
        // Test 11: AND (AND_RES)
        test_operation(5'b01010, 32'hF0F0F0F0, 32'h0F0F0F0F, 32'h00000000, "AND");
        test_operation(5'b01010, 32'hFFFFFFFF, 32'hAAAAAAAA, 32'hAAAAAAAA, "AND_MASK");
        
        // Test 12: Multiplication (MUL_RES)
        test_operation(5'b01011, 32'h00000010, 32'h00000020, 32'h00000200, "MUL");
        test_operation(5'b01011, 32'hFFFFFFFF, 32'h00000002, 32'hFFFFFFFE, "MUL_NEG");
        
        // Test 13: Multiplication High Signed (MULH_RES)
        test_operation(5'b01100, 32'h80000000, 32'h80000000, 32'h40000000, "MULH");
        
        // Test 14: Multiplication High Signed*Unsigned (MULHSU_RES)
        test_operation(5'b01101, 32'hFFFFFFFF, 32'h80000000, 32'h7FFFFFFF, "MULHSU");
        
        // Test 15: Multiplication High Unsigned (MULHU_RES)
        test_operation(5'b01110, 32'hFFFFFFFF, 32'hFFFFFFFF, 32'hFFFFFFFE, "MULHU");
        
        // Test 16: Division (DIV_RES)
        test_operation(5'b01111, 32'h00000100, 32'h00000010, 32'h00000010, "DIV");
        test_operation(5'b01111, 32'hFFFFFFF0, 32'h00000002, 32'hFFFFFFF8, "DIV_NEG");
        
        // Test 17: Division Unsigned (DIVU_RES)
        test_operation(5'b10000, 32'hFFFFFFF0, 32'h00000002, 32'h7FFFFFF8, "DIVU");
        
        // Test 18: Remainder (REM_RES)
        test_operation(5'b10001, 32'h00000017, 32'h00000005, 32'h00000003, "REM");
        test_operation(5'b10001, 32'hFFFFFFF9, 32'h00000005, 32'hFFFFFFFE, "REM_NEG");
        
        // Test 19: Remainder Unsigned (REMU_RES)
        test_operation(5'b10010, 32'h00000017, 32'h00000005, 32'h00000003, "REMU");
        
        // Test 20: Default case
        test_operation(5'b11111, 32'h12345678, 32'hABCDEF00, 32'h00000000, "DEFAULT");
        
        $display("\n=== ALU Testbench Completed ===");
        $finish;
    end
    
    // Generate VCD file for waveform viewing
    initial begin
        $dumpfile("alu_tb.vcd");
        $dumpvars(0, alu_tb);
    end
    
endmodule

src/EX_Stage/ALU/alu_tb.vcd
$date
	Thu Jul 10 21:44:17 2025
$end
$version
	Icarus Verilog
$end
$timescale
	1ps
$end
$scope module alu_tb $end
$var wire 32 ! RESULT [31:0] $end
$var reg 32 " DATA1 [31:0] $end
$var reg 32 # DATA2 [31:0] $end
$var reg 5 $ SELECT [4:0] $end
$scope module dut $end
$var wire 32 % AND_RES [31:0] $end
$var wire 32 & DATA1 [31:0] $end
$var wire 32 ' DATA2 [31:0] $end
$var wire 32 ( FWD_RES [31:0] $end
$var wire 32 ) OR_RES [31:0] $end
$var wire 5 * SELECT [4:0] $end
$var wire 32 + XOR_RES [31:0] $end
$var wire 32 , SUB_RES [31:0] $end
$var wire 32 - SRL_RES [31:0] $end
$var wire 32 . SRA_RES [31:0] $end
$var wire 32 / SLT_RES [31:0] $end
$var wire 32 0 SLTU_RES [31:0] $end
$var wire 32 1 SLL_RES [31:0] $end
$var wire 32 2 REM_RES [31:0] $end
$var wire 32 3 REMU_RES [31:0] $end
$var wire 32 4 MUL_RES [31:0] $end
$var wire 64 5 MULTIPICATION [63:0] $end
$var wire 32 6 MULH_RES [31:0] $end
$var wire 64 7 MULHU_TEMP [63:0] $end
$var wire 32 8 MULHU_RES [31:0] $end
$var wire 64 9 MULHSU_TEMP [63:0] $end
$var wire 32 : MULHSU_RES [31:0] $end
$var wire 32 ; DIV_RES [31:0] $end
$var wire 32 < DIVU_RES [31:0] $end
$var wire 32 = ADD_RES [31:0] $end
$var reg 32 > RESULT [31:0] $end
$upscope $end
$scope task display_result $end
$var reg 32 ? data1 [31:0] $end
$var reg 32 @ data2 [31:0] $end
$var reg 32 A expected [31:0] $end
$var reg 5 B op_code [4:0] $end
$var reg 80 C operation_name [79:0] $end
$upscope $end
$scope task test_operation $end
$var reg 32 D data1 [31:0] $end
$var reg 32 E data2 [31:0] $end
$var reg 32 F expected [31:0] $end
$var reg 5 G op_code [4:0] $end
$var reg 80 H operation_name [79:0] $end
$upscope $end
$upscope $end
$enddefinitions $end
$comment Show the parameter values. $end
$dumpall
$end
#0
$dumpvars
bx H
bx G
bx F
bx E
bx D
bx C
bx B
bx A
bx @
bx ?
bx >
bx =
bx <
bx ;
bx :
b0 9
bx 8
b0 7
bx 6
b0 5
bx 4
bx 3
bx 2
bx 1
bx 0
bx /
bx .
bx -
bx ,
bx +
b0 *
bx )
bx (
b0 '
b0 &
bx %
b0 $
b0 #
b0 "
bx !
$end
#1000
b0 1
b0 -
b0 .
b0 +
b0 )
b0 %
b0 /
b0 0
#2000
b0 =
b0 ,
#3000
b0 !
b0 >
b0 6
b0 8
b0 :
b0 (
b0 4
#5000
b10001100101011101000100 C
b10101011110011011110111100000000 A
b10101011110011011110111100000000 @
b10010001101000101011001111000 ?
b0 B
b1111101000000011010001000011001001000010110100100000100000000000 5
b110000110111100110101010101001000010110100100000100000000000 7
b110000110111100110101010101001000010110100100000100000000000 9
b10101011110011011110111100000000 #
b10101011110011011110111100000000 '
b10010001101000101011001111000 "
b10010001101000101011001111000 &
b10001100101011101000100 H
b10101011110011011110111100000000 F
b10101011110011011110111100000000 E
b10010001101000101011001111000 D
b0 G
#6000
b1 0
b10000001000100011000000000 %
b10111011111111011111111101111000 )
b10111001111110011011100101111000 +
b10010001101000101011001111000 1
b10010001101000101011001111000 -
b10010001101000101011001111000 .
#7000
b10111110000000100100010101111000 =
b1100110011001100110011101111000 ,
#8000
b10101011110011011110111100000000 !
b10101011110011011110111100000000 >
b11111010000000110100010000110010 6
b1100001101111001101010101010 8
b1100001101111001101010101010 :
b10101011110011011110111100000000 (
b1000010110100100000100000000000 4
b0 ;
b0 <
b10010001101000101011001111000 2
b10010001101000101011001111000 3
#15000
b10111110000000100100010101111000 !
b10111110000000100100010101111000 >
b10000010100010001000100 C
b110000 A
b100000 @
b10000 ?
b1 B
b1 $
b1 *
b100000 #
b100000 '
b1000000000 5
b1000000000 7
b1000000000 9
b10000 "
b10000 &
b10000010100010001000100 H
b110000 F
b100000 E
b10000 D
b1 G
#16000
b1 /
b0 %
b110000 )
b110000 +
b10000 1
b10000 -
b10000 .
#17000
b110000 !
b110000 >
b110000 =
b11111111111111111111111111110000 ,
#18000
b0 6
b0 8
b0 :
b100000 (
b1000000000 4
b10000 2
b10000 3
#25000
b1000001010001000100010001011111010011110101011001000110 C
b0 A
b1 @
b11111111111111111111111111111111 ?
b1 #
b1 '
b1111111111111111111111111111111111111111111111111111111111111111 5
b11111111111111111111111111111111 7
b11111111111111111111111111111111 9
b11111111111111111111111111111111 "
b11111111111111111111111111111111 &
b1000001010001000100010001011111010011110101011001000110 H
b0 F
b1 E
b11111111111111111111111111111111 D
#26000
b1 %
b11111111111111111111111111111111 )
b11111111111111111111111111111110 +
b0 0
b11111111111111111111111111111110 1
b1111111111111111111111111111111 -
b11111111111111111111111111111111 .
#27000
b0 !
b0 >
b0 =
b11111111111111111111111111111110 ,
#28000
b11111111111111111111111111111111 6
b1 (
b11111111111111111111111111111111 ;
b11111111111111111111111111111111 4
b11111111111111111111111111111111 <
b0 2
b0 3
#35000
b11111111111111111111111111111110 !
b11111111111111111111111111111110 >
b10100110101010101000010 C
b10000 A
b10000 @
b100000 ?
b10 B
b10 $
b10 *
b10000 #
b10000 '
b1000000000 5
b1000000000 7
b1000000000 9
b100000 "
b100000 &
b10100110101010101000010 H
b10000 F
b10000 E
b100000 D
b10 G
#36000
b0 %
b110000 )
b110000 +
b0 /
b1000000000000000000000 1
b0 -
b0 .
#37000
b10000 !
b10000 >
b110000 =
b10000 ,
#38000
b0 6
b10000 (
b1000000000 4
b10 ;
b10 <
#45000
b1010011010101010100001001011111010011100100010101000111 C
b11111111111111111111111111110000 A
b100000 @
b10000 ?
b100000 #
b100000 '
b1000000000 5
b1000000000 7
b1000000000 9
b10000 "
b10000 &
b1010011010101010100001001011111010011100100010101000111 H
b11111111111111111111111111110000 F
b100000 E
b10000 D
#46000
b10000 -
b10000 .
b1 /
b1 0
b10000 1
#47000
b11111111111111111111111111110000 !
b11111111111111111111111111110000 >
b11111111111111111111111111110000 ,
#48000
b100000 (
b10000 2
b10000 3
b0 ;
b0 <
#55000
b10000 !
b10000 >
b10100110100110001001100 C
b10000 A
b100 @
b1 ?
b11 B
b11 $
b11 *
b100 #
b100 '
b100 5
b100 7
b100 9
b1 "
b1 &
b10100110100110001001100 H
b10000 F
b100 E
b1 D
b11 G
#56000
b101 )
b101 +
b0 -
b0 .
#57000
b101 =
b11111111111111111111111111111101 ,
#58000
b100 (
b100 4
b1 2
b1 3
#65000
b1010011010011000100110000110010 C
b11000011110000111100001111000000 A
b10 @
b11110000111100001111000011110000 ?
b10 #
b10 '
b1111111111111111111111111111111111100001111000011110000111100000 5
b111100001111000011110000111100000 7
b111100001111000011110000111100000 9
b11110000111100001111000011110000 "
b11110000111100001111000011110000 &
b1010011010011000100110000110010 H
b11000011110000111100001111000000 F
b10 E
b11110000111100001111000011110000 D
#66000
b11000011110000111100001111000000 !
b11000011110000111100001111000000 >
b11110000111100001111000011110010 )
b11110000111100001111000011110010 +
b0 0
b11000011110000111100001111000000 1
b111100001111000011110000111100 -
b11111100001111000011110000111100 .
#67000
b11110000111100001111000011110010 =
b11110000111100001111000011101110 ,
#68000
b11111111111111111111111111111111 6
b1 8
b1 :
b10 (
b11100001111000011110000111100000 4
b11111000011110000111100001111000 ;
b1111000011110000111100001111000 <
b0 2
b0 3
#75000
b1 !
b1 >
b101001101001100010101000101111101010100 C
b1 A
b100000 @
b10000 ?
b100 B
b100 $
b100 *
b100000 #
b100000 '
b1000000000 5
b1000000000 7
b1000000000 9
b10000 "
b10000 &
b101001101001100010101000101111101010100 H
b1 F
b100000 E
b10000 D
b100 G
#76000
b1 0
b110000 )
b110000 +
b10000 1
b10000 -
b10000 .
#77000
b110000 =
b11111111111111111111111111110000 ,
#78000
b0 6
b0 8
b0 :
b100000 (
b10000 2
b10000 3
b1000000000 4
b0 ;
b0 <
#85000
b101001101001100010101000101111101000110 C
b0 A
b10000 @
b100000 ?
b10000 #
b10000 '
b1000000000 5
b1000000000 7
b1000000000 9
b100000 "
b100000 &
b101001101001100010101000101111101000110 H
b0 F
b10000 E
b100000 D
#86000
b0 !
b0 >
b0 /
b0 0
b1000000000000000000000 1
b0 -
b0 .
#87000
b10000 ,
#88000
b10000 (
b10 ;
b10 <
b0 2
b0 3
#95000
b1010011010011000101010001011111010011100100010101000111 C
b1 A
b11111111111111111111111111110000 ?
b1111111111111111111111111111111111111111111111111111111100000000 5
b111111111111111111111111111100000000 7
b111111111111111111111111111100000000 9
b11111111111111111111111111110000 "
b11111111111111111111111111110000 &
b1010011010011000101010001011111010011100100010101000111 H
b1 F
b11111111111111111111111111110000 D
#96000
b1 !
b1 >
b10000 %
b11111111111111111111111111110000 )
b11111111111111111111111111100000 +
b1 /
b11111111111100000000000000000000 1
b1111111111111111 -
b11111111111111111111111111111111 .
#97000
b0 =
b11111111111111111111111111100000 ,
#98000
b11111111111111111111111111111111 6
b1111 8
b1111 :
b11111111111111111111111100000000 4
b11111111111111111111111111111111 ;
b1111111111111111111111111111 <
#105000
b0 !
b0 >
b10100110100110001010100010101010101111101010100 C
b100000 @
b10000 ?
b101 B
b101 $
b101 *
b100000 #
b100000 '
b1000000000 5
b1000000000 7
b1000000000 9
b10000 "
b10000 &
b10100110100110001010100010101010101111101010100 H
b100000 E
b10000 D
b101 G
#106000
b1 !
b1 >
b1 0
b0 %
b110000 )
b110000 +
b10000 1
b10000 -
b10000 .
#107000
b110000 =
b11111111111111111111111111110000 ,
#108000
b0 6
b0 8
b0 :
b100000 (
b10000 2
b10000 3
b1000000000 4
b0 ;
b0 <
#115000
b10100110100110001010100010101010101111101000110 C
b0 A
b10000 @
b11111111111111111111111111110000 ?
b10000 #
b10000 '
b1111111111111111111111111111111111111111111111111111111100000000 5
b111111111111111111111111111100000000 7
b111111111111111111111111111100000000 9
b11111111111111111111111111110000 "
b11111111111111111111111111110000 &
b10100110100110001010100010101010101111101000110 H
b0 F
b10000 E
b11111111111111111111111111110000 D
#116000
b0 !
b0 >
b10000 %
b11111111111111111111111111110000 )
b11111111111111111111111111100000 +
b0 0
b11111111111100000000000000000000 1
b1111111111111111 -
b11111111111111111111111111111111 .
#117000
b0 =
b11111111111111111111111111100000 ,
#118000
b11111111111111111111111111111111 6
b1111 8
b1111 :
b10000 (
b11111111111111111111111111111111 ;
b0 3
b11111111111111111111111100000000 4
b1111111111111111111111111111 <
b0 2
#125000
b11111111111111111111111111100000 !
b11111111111111111111111111100000 >
b10110000100111101010010 C
b11111111111111111111111111111111 A
b1111000011110000111100001111 @
b11110000111100001111000011110000 ?
b110 B
b110 $
b110 *
b1111000011110000111100001111 #
b1111000011110000111100001111 '
b1111111100011101001110110101100101101010010011000010111000010000 5
b111000101100010010100110100001101010010011000010111000010000 7
b111000101100010010100110100001101010010011000010111000010000 9
b11110000111100001111000011110000 "
b11110000111100001111000011110000 &
b10110000100111101010010 H
b11111111111111111111111111111111 F
b1111000011110000111100001111 E
b11110000111100001111000011110000 D
b110 G
#126000
b11111111111111111111111111111111 !
b11111111111111111111111111111111 >
b0 %
b11111111111111111111111111111111 )
b11111111111111111111111111111111 +
b1111000011110000000000000000000 1
b11110000111100001 -
b11111111111111111110000111100001 .
#127000
b11111111111111111111111111111111 =
b11100001111000011110000111100001 ,
#128000
b11111111000111010011101101011001 6
b1110001011000100101001101000 8
b1110001011000100101001101000 :
b1111000011110000111100001111 (
b11111111111111111111111111111111 2
b1101010010011000010111000010000 4
b10000 <
#135000
b101100001001111010100100101111101010011010000010100110101000101 C
b0 A
b10101010101010101010101010101010 @
b10101010101010101010101010101010 ?
b10101010101010101010101010101010 #
b10101010101010101010101010101010 '
b1110001110001110001110001110011100011100011100011100011100100 5
b111000111000111000111000111000011100011100011100011100011100100 7
b111000111000111000111000111000011100011100011100011100011100100 9
b10101010101010101010101010101010 "
b10101010101010101010101010101010 &
b101100001001111010100100101111101010011010000010100110101000101 H
b0 F
b10101010101010101010101010101010 E
b10101010101010101010101010101010 D
#136000
b0 !
b0 >
b0 /
b10101010101010101010101010101010 %
b10101010101010101010101010101010 )
b0 +
b10101010101010101010100000000000 1
b1010101010101010101010 -
b11111111111010101010101010101010 .
#137000
b1010101010101010101010101010100 =
b0 ,
#138000
b11100011100011100011100011100 6
b1110001110001110001110001110000 8
b1110001110001110001110001110000 :
b10101010101010101010101010101010 (
b11100011100011100011100011100100 4
b1 ;
b1 <
b0 2
#145000
b1010101010101010101010 !
b1010101010101010101010 >
b10100110101001001001100 C
b1000000000000000000000000000 A
b100 @
b10000000000000000000000000000000 ?
b111 B
b111 $
b111 *
b100 #
b100 '
b1111111111111111111111111111111000000000000000000000000000000000 5
b1000000000000000000000000000000000 7
b1000000000000000000000000000000000 9
b10000000000000000000000000000000 "
b10000000000000000000000000000000 &
b10100110101001001001100 H
b1000000000000000000000000000 F
b100 E
b10000000000000000000000000000000 D
b111 G
#146000
b1000000000000000000000000000 !
b1000000000000000000000000000 >
b0 %
b10000000000000000000000000000100 )
b10000000000000000000000000000100 +
b1 /
b0 1
b1000000000000000000000000000 -
b11111000000000000000000000000000 .
#147000
b10000000000000000000000000000100 =
b1111111111111111111111111111100 ,
#148000
b11111111111111111111111111111110 6
b10 8
b10 :
b100 (
b11100000000000000000000000000000 ;
b0 4
b100000000000000000000000000000 <
#155000
b1010011010100100100110000110010 C
b111100001111000011110000111100 A
b10 @
b11110000111100001111000011110000 ?
b10 #
b10 '
b1111111111111111111111111111111111100001111000011110000111100000 5
b111100001111000011110000111100000 7
b111100001111000011110000111100000 9
b11110000111100001111000011110000 "
b11110000111100001111000011110000 &
b1010011010100100100110000110010 H
b111100001111000011110000111100 F
b10 E
b11110000111100001111000011110000 D
#156000
b111100001111000011110000111100 !
b111100001111000011110000111100 >
b11110000111100001111000011110010 )
b11110000111100001111000011110010 +
b11000011110000111100001111000000 1
b111100001111000011110000111100 -
b11111100001111000011110000111100 .
#157000
b11110000111100001111000011110010 =
b11110000111100001111000011101110 ,
#158000
b11111111111111111111111111111111 6
b1 8
b1 :
b10 (
b11100001111000011110000111100000 4
b11111000011110000111100001111000 ;
b1111000011110000111100001111000 <
#165000
b11111100001111000011110000111100 !
b11111100001111000011110000111100 >
b10100110101001001000001 C
b11111000000000000000000000000000 A
b100 @
b10000000000000000000000000000000 ?
b1000 B
b1000 $
b1000 *
b100 #
b100 '
b1111111111111111111111111111111000000000000000000000000000000000 5
b1000000000000000000000000000000000 7
b1000000000000000000000000000000000 9
b10000000000000000000000000000000 "
b10000000000000000000000000000000 &
b10100110101001001000001 H
b11111000000000000000000000000000 F
b100 E
b10000000000000000000000000000000 D
b1000 G
#166000
b11111000000000000000000000000000 !
b11111000000000000000000000000000 >
b10000000000000000000000000000100 )
b10000000000000000000000000000100 +
b0 1
b1000000000000000000000000000 -
b11111000000000000000000000000000 .
#167000
b10000000000000000000000000000100 =
b1111111111111111111111111111100 ,
#168000
b11111111111111111111111111111110 6
b10 8
b10 :
b100 (
b0 4
b11100000000000000000000000000000 ;
b100000000000000000000000000000 <
#175000
b1010011010100100100000101011111010100000100111101010011 C
b111111111111111111111111111 A
b1111111111111111111111111111111 ?
b111111111111111111111111111111100 5
b111111111111111111111111111111100 7
b111111111111111111111111111111100 9
b1111111111111111111111111111111 "
b1111111111111111111111111111111 &
b1010011010100100100000101011111010100000100111101010011 H
b111111111111111111111111111 F
b1111111111111111111111111111111 D
#176000
b111111111111111111111111111 !
b111111111111111111111111111 >
b100 %
b1111111111111111111111111111111 )
b1111111111111111111111111111011 +
b0 /
b11111111111111111111111111110000 1
b111111111111111111111111111 -
b111111111111111111111111111 .
#177000
b10000000000000000000000000000011 =
b1111111111111111111111111111011 ,
#178000
b1 6
b1 8
b1 :
b11111111111111111111111111111100 4
b11111111111111111111111111111 ;
b11111111111111111111111111111 <
b11 2
b11 3
#185000
b1111111111111111111111111111111 !
b1111111111111111111111111111111 >
b100111101010010 C
b11111111111111111111111111111111 A
b1111000011110000111100001111 @
b11110000111100001111000011110000 ?
b1001 B
b1001 $
b1001 *
b1111000011110000111100001111 #
b1111000011110000111100001111 '
b1111111100011101001110110101100101101010010011000010111000010000 5
b111000101100010010100110100001101010010011000010111000010000 7
b111000101100010010100110100001101010010011000010111000010000 9
b11110000111100001111000011110000 "
b11110000111100001111000011110000 &
b100111101010010 H
b11111111111111111111111111111111 F
b1111000011110000111100001111 E
b11110000111100001111000011110000 D
b1001 G
#186000
b11111111111111111111111111111111 !
b11111111111111111111111111111111 >
b0 %
b11111111111111111111111111111111 )
b11111111111111111111111111111111 +
b1 /
b1111000011110000000000000000000 1
b11110000111100001 -
b11111111111111111110000111100001 .
#187000
b11111111111111111111111111111111 =
b11100001111000011110000111100001 ,
#188000
b11111111000111010011101101011001 6
b1110001011000100101001101000 8
b1110001011000100101001101000 :
b1111000011110000111100001111 (
b1101010010011000010111000010000 4
b11111111111111111111111111111111 ;
b10000 <
b11111111111111111111111111111111 2
b0 3
#195000
b10011110101001001011111010000010100110001001100 C
b11111111111111111111111111111111 @
b0 ?
b11111111111111111111111111111111 #
b11111111111111111111111111111111 '
b0 5
b0 7
b0 9
b0 "
b0 &
b10011110101001001011111010000010100110001001100 H
b11111111111111111111111111111111 E
b0 D
#196000
b0 /
b1 0
b0 1
b0 -
b0 .
#197000
b1 ,
#198000
b0 6
b0 8
b0 :
b11111111111111111111111111111111 (
b0 4
b0 ;
b0 <
b0 2
#205000
b0 !
b0 >
b10000010100111001000100 C
b0 A
b1111000011110000111100001111 @
b11110000111100001111000011110000 ?
b1010 B
b1010 $
b1010 *
b1111000011110000111100001111 #
b1111000011110000111100001111 '
b1111111100011101001110110101100101101010010011000010111000010000 5
b111000101100010010100110100001101010010011000010111000010000 7
b111000101100010010100110100001101010010011000010111000010000 9
b11110000111100001111000011110000 "
b11110000111100001111000011110000 &
b10000010100111001000100 H
b0 F
b1111000011110000111100001111 E
b11110000111100001111000011110000 D
b1010 G
#206000
b1111000011110000000000000000000 1
b0 0
b1 /
b11110000111100001 -
b11111111111111111110000111100001 .
#207000
b11100001111000011110000111100001 ,
#208000
b11111111000111010011101101011001 6
b1110001011000100101001101000 8
b1110001011000100101001101000 :
b1111000011110000111100001111 (
b10000 <
b11111111111111111111111111111111 2
b1101010010011000010111000010000 4
b11111111111111111111111111111111 ;
#215000
b100000101001110010001000101111101001101010000010101001101001011 C
b10101010101010101010101010101010 A
b10101010101010101010101010101010 @
b11111111111111111111111111111111 ?
b10101010101010101010101010101010 #
b10101010101010101010101010101010 '
b1010101010101010101010101010110 5
b1010101010101010101010101010100101010101010101010101010101010110 7
b1010101010101010101010101010100101010101010101010101010101010110 9
b11111111111111111111111111111111 "
b11111111111111111111111111111111 &
b100000101001110010001000101111101001101010000010101001101001011 H
b10101010101010101010101010101010 F
b10101010101010101010101010101010 E
b11111111111111111111111111111111 D
#216000
b10101010101010101010101010101010 !
b10101010101010101010101010101010 >
b0 /
b10101010101010101010101010101010 %
b1010101010101010101010101010101 +
b11111111111111111111110000000000 1
b1111111111111111111111 -
b11111111111111111111111111111111 .
#217000
b10101010101010101010101010101001 =
b1010101010101010101010101010101 ,
#218000
b0 6
b10101010101010101010101010101001 8
b10101010101010101010101010101001 :
b10101010101010101010101010101010 (
b1010101010101010101010101010101 3
b1010101010101010101010101010110 4
b0 ;
b1 <
#225000
b1010101010101010101010101010110 !
b1010101010101010101010101010110 >
b10011010101010101001100 C
b1000000000 A
b100000 @
b10000 ?
b1011 B
b1011 $
b1011 *
b100000 #
b100000 '
b1000000000 5
b1000000000 7
b1000000000 9
b10000 "
b10000 &
b10011010101010101001100 H
b1000000000 F
b100000 E
b10000 D
b1011 G
#226000
b1 /
b0 %
b110000 )
b110000 +
b1 0
b10000 1
b10000 -
b10000 .
#227000
b110000 =
b11111111111111111111111111110000 ,
#228000
b1000000000 !
b1000000000 >
b0 8
b0 :
b100000 (
b1000000000 4
b0 <
b10000 2
b10000 3
