src/MA_Stage/DMEM/data_memory.v
`timescale 1ns / 1ps

// Define a module called "DATA_MEMORY"
module DATA_MEMORY (CLK, RESET, WRITE, READ, ADDR, DATA_IN, DATA_OUT);

    // Inputs and Outputs
    input CLK;
    input RESET;
    input [1:0] WRITE, READ;
    input [31:0] ADDR, DATA_IN;
    output reg [31:0] DATA_OUT;

    reg [31:0] mem [0:1023];  // 4KB word-addressable memory
    integer i;

    // Write Operation
    always @(posedge CLK) begin
        if (!RESET) begin  // Fixed: Active low reset logic
            case (WRITE)
                2'b01: begin  // Byte write
                    case (ADDR[1:0])
                        2'b00: mem[ADDR[11:2]][7:0]   <= DATA_IN[7:0];
                        2'b01: mem[ADDR[11:2]][15:8]  <= DATA_IN[7:0];
                        2'b10: mem[ADDR[11:2]][23:16] <= DATA_IN[7:0];
                        2'b11: mem[ADDR[11:2]][31:24] <= DATA_IN[7:0];
                    endcase
                end
                2'b10: begin  // Half-word write
                    if (ADDR[0] == 1'b0) begin  // Half-word aligned
                        case (ADDR[1])
                            1'b0: mem[ADDR[11:2]][15:0]  <= DATA_IN[15:0];
                            1'b1: mem[ADDR[11:2]][31:16] <= DATA_IN[15:0];
                        endcase
                    end
                end
                2'b11: begin  // Word write
                    if (ADDR[1:0] == 2'b00) begin  // Word aligned
                        mem[ADDR[11:2]] <= DATA_IN;
                    end
                end
            endcase
        end
    end

    // Read Operation
    always @(*) begin
        if (RESET) begin
            for (i=0; i<256; i=i+1)
                mem[i] = 32'b0;
            DATA_OUT = 32'd0;
        end else begin
            case (READ)
                2'b01: begin  // Byte read
                    case (ADDR[1:0])
                        2'b00: DATA_OUT = {24'b0, mem[ADDR[11:2]][7:0]};
                        2'b01: DATA_OUT = {24'b0, mem[ADDR[11:2]][15:8]};
                        2'b10: DATA_OUT = {24'b0, mem[ADDR[11:2]][23:16]};
                        2'b11: DATA_OUT = {24'b0, mem[ADDR[11:2]][31:24]};
                    endcase
                end
                2'b10: begin  // Half-word read
                    if (ADDR[0] == 1'b0) begin
                        case (ADDR[1])
                            1'b0: DATA_OUT = {16'b0, mem[ADDR[11:2]][15:0]};
                            1'b1: DATA_OUT = {16'b0, mem[ADDR[11:2]][31:16]};
                        endcase
                    end else begin
                        DATA_OUT = 32'd0;
                    end
                end
                2'b11: begin  // Word read
                    if (ADDR[1:0] == 2'b00) begin
                        DATA_OUT = mem[ADDR[11:2]];
                    end else begin
                        DATA_OUT = 32'd0;
                    end
                end
                default: DATA_OUT = 32'd0;
            endcase
        end
    end

    // Initialize memory for testing
    initial begin
        mem[0] = 32'h00000000;
        mem[1] = 32'h12345678;
        mem[2] = 32'hABCDEF00;
        mem[3] = 32'hDEADBEEF;
        mem[4] = 32'hCAFEBABE;
    end

endmodule

src/MA_Stage/DMEM/data_memory_tb.v
`timescale 1ns/1ps

module data_memory_tb();
    // Testbench signals
    reg CLK;
    reg RESET;
    reg [1:0] WRITE, READ;
    reg [31:0] ADDR, DATA_IN;
    wire [31:0] DATA_OUT;
    
    // Instantiate the DATA_MEMORY module
    DATA_MEMORY dut (
        .CLK(CLK),
        .RESET(RESET),
        .WRITE(WRITE),
        .READ(READ),
        .ADDR(ADDR),
        .DATA_IN(DATA_IN),
        .DATA_OUT(DATA_OUT)
    );
    
    // Clock generation
    initial begin
        CLK = 0;
        forever #5 CLK = ~CLK; // 10ns period (100MHz)
    end
    
    // Task to perform write operation
    task write_memory;
        input [1:0] write_type;
        input [31:0] address;
        input [31:0] data;
        input [63:0] test_name; // 8 characters
        begin
            @(posedge CLK);
            WRITE = write_type;
            READ = 2'b00;
            ADDR = address;
            DATA_IN = data;
            @(posedge CLK);
            WRITE = 2'b00;
            $display("WRITE %0s: Addr=%h, Data=%h, Type=%b", test_name, address, data, write_type);
        end
    endtask
    
    // Task to perform read operation
    task read_memory;
        input [1:0] read_type;
        input [31:0] address;
        input [31:0] expected;
        input [63:0] test_name; // 8 characters
        begin
            @(posedge CLK);
            READ = read_type;
            WRITE = 2'b00;
            ADDR = address;
            @(posedge CLK);
            #1; // Wait for combinational logic
            $display("READ  %0s: Addr=%h, Data=%h, Expected=%h, Type=%b %s", 
                     test_name, address, DATA_OUT, expected, read_type,
                     (DATA_OUT == expected) ? "PASS" : "FAIL");
            READ = 2'b00;
        end
    endtask
    
    initial begin
        $display("=== Data Memory Testbench Started ===");
        $display("Operation | Address  | Data     | Expected | Type | Result");
        $display("----------|----------|----------|----------|------|-------");
        
        // Initialize signals
        RESET = 1;
        WRITE = 2'b00;
        READ = 2'b00;
        ADDR = 32'h00000000;
        DATA_IN = 32'h00000000;
        
        // Apply reset
        repeat(3) @(posedge CLK);
        RESET = 0;
        repeat(2) @(posedge CLK);
        
        $display("\n=== Testing Word Operations (32-bit) ===");
        
        // Test word write and read
        write_memory(2'b11, 32'h00000000, 32'hDEADBEEF, "WORD_W1");
        read_memory(2'b11, 32'h00000000, 32'hDEADBEEF, "WORD_R1");
        
        write_memory(2'b11, 32'h00000004, 32'hCAFEBABE, "WORD_W2");
        read_memory(2'b11, 32'h00000004, 32'hCAFEBABE, "WORD_R2");
        
        write_memory(2'b11, 32'h00000008, 32'h12345678, "WORD_W3");
        read_memory(2'b11, 32'h00000008, 32'h12345678, "WORD_R3");
        
        // Test unaligned word access (should return 0 or not work)
        read_memory(2'b11, 32'h00000001, 32'h00000000, "WORD_UA");
        read_memory(2'b11, 32'h00000002, 32'h00000000, "WORD_UB");
        read_memory(2'b11, 32'h00000003, 32'h00000000, "WORD_UC");
        
        $display("\n=== Testing Half-word Operations (16-bit) ===");
        
        // Test half-word write and read
        write_memory(2'b10, 32'h00000010, 32'h0000ABCD, "HALF_W1");
        read_memory(2'b10, 32'h00000010, 32'h0000ABCD, "HALF_R1");
        
        write_memory(2'b10, 32'h00000012, 32'h0000EF12, "HALF_W2");
        read_memory(2'b10, 32'h00000012, 32'h0000EF12, "HALF_R2");
        
        // Read the full word to verify both halves
        read_memory(2'b11, 32'h00000010, 32'hEF12ABCD, "HALF_FW");
        
        // Test unaligned half-word access
        read_memory(2'b10, 32'h00000011, 32'h00000000, "HALF_UA");
        read_memory(2'b10, 32'h00000013, 32'h00000000, "HALF_UB");
        
        $display("\n=== Testing Byte Operations (8-bit) ===");
        
        // Test byte write and read at different positions
        write_memory(2'b01, 32'h00000020, 32'h000000AA, "BYTE_W0");  // Byte 0
        read_memory(2'b01, 32'h00000020, 32'h000000AA, "BYTE_R0");
        
        write_memory(2'b01, 32'h00000021, 32'h000000BB, "BYTE_W1");  // Byte 1
        read_memory(2'b01, 32'h00000021, 32'h000000BB, "BYTE_R1");
        
        write_memory(2'b01, 32'h00000022, 32'h000000CC, "BYTE_W2");  // Byte 2
        read_memory(2'b01, 32'h00000022, 32'h000000CC, "BYTE_R2");
        
        write_memory(2'b01, 32'h00000023, 32'h000000DD, "BYTE_W3");  // Byte 3
        read_memory(2'b01, 32'h00000023, 32'h000000DD, "BYTE_R3");
        
        // Read the full word to verify all bytes
        read_memory(2'b11, 32'h00000020, 32'hDDCCBBAA, "BYTE_FW");
        
        $display("\n=== Testing Mixed Operations ===");
        
        // Write a word, then read as bytes
        write_memory(2'b11, 32'h00000030, 32'h12345678, "MIX_WW");
        read_memory(2'b01, 32'h00000030, 32'h00000078, "MIX_RB0"); // LSB
        read_memory(2'b01, 32'h00000031, 32'h00000056, "MIX_RB1");
        read_memory(2'b01, 32'h00000032, 32'h00000034, "MIX_RB2");
        read_memory(2'b01, 32'h00000033, 32'h00000012, "MIX_RB3"); // MSB
        
        // Write a word, then read as half-words
        read_memory(2'b10, 32'h00000030, 32'h00005678, "MIX_RH0"); // Lower half
        read_memory(2'b10, 32'h00000032, 32'h00001234, "MIX_RH1"); // Upper half
        
        $display("\n=== Testing Reset Functionality ===");
        
        // Reset the memory
        RESET = 1;
        repeat(2) @(posedge CLK);
        
        // All reads should return 0 during reset
        read_memory(2'b11, 32'h00000000, 32'h00000000, "RST_R1");
        read_memory(2'b11, 32'h00000004, 32'h00000000, "RST_R2");
        
        // Release reset
        RESET = 0;
        repeat(2) @(posedge CLK);
        
        // Memory should be cleared
        read_memory(2'b11, 32'h00000000, 32'h00000000, "CLR_R1");
        read_memory(2'b11, 32'h00000004, 32'h00000000, "CLR_R2");
        
        $display("\n=== Testing Edge Cases ===");
        
        // Test boundary addresses
        write_memory(2'b11, 32'h00000FFC, 32'hFFFFFFFF, "EDGE_W1"); // Last word
        read_memory(2'b11, 32'h00000FFC, 32'hFFFFFFFF, "EDGE_R1");
        
        // Test no operation cases
        @(posedge CLK);
        WRITE = 2'b00;
        READ = 2'b00;
        ADDR = 32'h00000040;
        @(posedge CLK);
        #1;
        $display("NO_OP: DATA_OUT = %h (should be previous value or 0)", DATA_OUT);
        
        $display("\n=== Data Memory Testbench Completed ===");
        $finish;
    end
    
    // Generate VCD file for waveform viewing
    initial begin
        $dumpfile("data_memory_tb.vcd");
        $dumpvars(0, data_memory_tb);
    end
    
endmodule

src/MA_Stage/DMEM/data_memory_tb.vcd
$date
	Thu Jul 10 22:41:02 2025
$end
$version
	Icarus Verilog
$end
$timescale
	1ps
$end
$scope module data_memory_tb $end
$var wire 32 ! DATA_OUT [31:0] $end
$var reg 32 " ADDR [31:0] $end
$var reg 1 # CLK $end
$var reg 32 $ DATA_IN [31:0] $end
$var reg 2 % READ [1:0] $end
$var reg 1 & RESET $end
$var reg 2 ' WRITE [1:0] $end
$scope module dut $end
$var wire 32 ( ADDR [31:0] $end
$var wire 1 # CLK $end
$var wire 32 ) DATA_IN [31:0] $end
$var wire 2 * READ [1:0] $end
$var wire 1 & RESET $end
$var wire 2 + WRITE [1:0] $end
$var reg 32 , DATA_OUT [31:0] $end
$var integer 32 - i [31:0] $end
$upscope $end
$scope task read_memory $end
$var reg 32 . address [31:0] $end
$var reg 32 / expected [31:0] $end
$var reg 2 0 read_type [1:0] $end
$var reg 64 1 test_name [63:0] $end
$upscope $end
$scope task write_memory $end
$var reg 32 2 address [31:0] $end
$var reg 32 3 data [31:0] $end
$var reg 64 4 test_name [63:0] $end
$var reg 2 5 write_type [1:0] $end
$upscope $end
$upscope $end
$enddefinitions $end
$comment Show the parameter values. $end
$dumpall
$end
#0
$dumpvars
bx 5
bx 4
bx 3
bx 2
bx 1
bx 0
bx /
bx .
b100000000 -
b0 ,
b0 +
b0 *
b0 )
b0 (
b0 '
1&
b0 %
b0 $
0#
b0 "
b0 !
$end
#5000
1#
#10000
0#
#15000
1#
#20000
0#
#25000
0&
1#
#30000
0#
#35000
1#
#40000
0#
#45000
b1010111010011110101001001000100010111110101011100110001 4
b11011110101011011011111011101111 3
b0 2
b11 5
1#
#50000
0#
#55000
b11011110101011011011111011101111 $
b11011110101011011011111011101111 )
b11 '
b11 +
1#
#60000
0#
#65000
b1010111010011110101001001000100010111110101001000110001 1
b11011110101011011011111011101111 /
b0 .
b11 0
b0 '
b0 +
1#
#70000
0#
#75000
b11011110101011011011111011101111 !
b11011110101011011011111011101111 ,
b11 %
b11 *
1#
#80000
0#
#85000
1#
#86000
b0 !
b0 ,
b1010111010011110101001001000100010111110101011100110010 4
b11001010111111101011101010111110 3
b100 2
b0 %
b0 *
#90000
0#
#95000
b11001010111111101011101010111110 $
b11001010111111101011101010111110 )
b100 "
b100 (
b11 '
b11 +
1#
#100000
0#
#105000
b1010111010011110101001001000100010111110101001000110010 1
b11001010111111101011101010111110 /
b100 .
b0 '
b0 +
1#
#110000
0#
#115000
b11001010111111101011101010111110 !
b11001010111111101011101010111110 ,
b11 %
b11 *
1#
#120000
0#
#125000
1#
#126000
b0 !
b0 ,
b1010111010011110101001001000100010111110101011100110011 4
b10010001101000101011001111000 3
b1000 2
b0 %
b0 *
#130000
0#
#135000
b10010001101000101011001111000 $
b10010001101000101011001111000 )
b1000 "
b1000 (
b11 '
b11 +
1#
#140000
0#
#145000
b1010111010011110101001001000100010111110101001000110011 1
b10010001101000101011001111000 /
b1000 .
b0 '
b0 +
1#
#150000
0#
#155000
b10010001101000101011001111000 !
b10010001101000101011001111000 ,
b11 %
b11 *
1#
#160000
0#
#165000
1#
#166000
b0 !
b0 ,
b1010111010011110101001001000100010111110101010101000001 1
b0 /
b1 .
b0 %
b0 *
#170000
0#
#175000
b1 "
b1 (
b11 %
b11 *
1#
#180000
0#
#185000
1#
#186000
b1010111010011110101001001000100010111110101010101000010 1
b10 .
b0 %
b0 *
#190000
0#
#195000
b10 "
b10 (
b11 %
b11 *
1#
#200000
0#
#205000
1#
#206000
b1010111010011110101001001000100010111110101010101000011 1
b11 .
b0 %
b0 *
#210000
0#
#215000
b11 "
b11 (
b11 %
b11 *
1#
#220000
0#
#225000
1#
#226000
b1001000010000010100110001000110010111110101011100110001 4
b1010101111001101 3
b10000 2
b10 5
b0 %
b0 *
#230000
0#
#235000
b1010101111001101 $
b1010101111001101 )
b10000 "
b10000 (
b10 '
b10 +
1#
#240000
0#
#245000
b1001000010000010100110001000110010111110101001000110001 1
b1010101111001101 /
b10000 .
b10 0
b0 '
b0 +
1#
#250000
0#
#255000
b1010101111001101 !
b1010101111001101 ,
b10 %
b10 *
1#
#260000
0#
#265000
1#
#266000
b0 !
b0 ,
b1001000010000010100110001000110010111110101011100110010 4
b1110111100010010 3
b10010 2
b0 %
b0 *
#270000
0#
#275000
b1110111100010010 $
b1110111100010010 )
b10010 "
b10010 (
b10 '
b10 +
1#
#280000
0#
#285000
b1001000010000010100110001000110010111110101001000110010 1
b1110111100010010 /
b10010 .
b0 '
b0 +
1#
#290000
0#
#295000
b1110111100010010 !
b1110111100010010 ,
b10 %
b10 *
1#
#300000
0#
#305000
1#
#306000
b0 !
b0 ,
b1001000010000010100110001000110010111110100011001010111 1
b11101111000100101010101111001101 /
b10000 .
b11 0
b0 %
b0 *
#310000
0#
#315000
b11101111000100101010101111001101 !
b11101111000100101010101111001101 ,
b10000 "
b10000 (
b11 %
b11 *
1#
#320000
0#
#325000
1#
#326000
b0 !
b0 ,
b1001000010000010100110001000110010111110101010101000001 1
b0 /
b10001 .
b10 0
b0 %
b0 *
#330000
0#
#335000
b10001 "
b10001 (
b10 %
b10 *
1#
#340000
0#
#345000
1#
#346000
b1001000010000010100110001000110010111110101010101000010 1
b10011 .
b0 %
b0 *
#350000
0#
#355000
b10011 "
b10011 (
b10 %
b10 *
1#
#360000
0#
#365000
1#
#366000
b1000010010110010101010001000101010111110101011100110000 4
b10101010 3
b100000 2
b1 5
b0 %
b0 *
#370000
0#
#375000
b10101010 $
b10101010 )
b100000 "
b100000 (
b1 '
b1 +
1#
#380000
0#
#385000
b1000010010110010101010001000101010111110101001000110000 1
b10101010 /
b100000 .
b1 0
b0 '
b0 +
1#
#390000
0#
#395000
b10101010 !
b10101010 ,
b1 %
b1 *
1#
#400000
0#
#405000
1#
#406000
b0 !
b0 ,
b1000010010110010101010001000101010111110101011100110001 4
b10111011 3
b100001 2
b0 %
b0 *
#410000
0#
#415000
b10111011 $
b10111011 )
b100001 "
b100001 (
b1 '
b1 +
1#
#420000
0#
#425000
b1000010010110010101010001000101010111110101001000110001 1
b10111011 /
b100001 .
b0 '
b0 +
1#
#430000
0#
#435000
b10111011 !
b10111011 ,
b1 %
b1 *
1#
#440000
0#
#445000
1#
#446000
b0 !
b0 ,
b1000010010110010101010001000101010111110101011100110010 4
b11001100 3
b100010 2
b0 %
b0 *
#450000
0#
#455000
b11001100 $
b11001100 )
b100010 "
b100010 (
b1 '
b1 +
1#
#460000
0#
#465000
b1000010010110010101010001000101010111110101001000110010 1
b11001100 /
b100010 .
b0 '
b0 +
1#
#470000
0#
#475000
b11001100 !
b11001100 ,
b1 %
b1 *
1#
#480000
0#
#485000
1#
#486000
b0 !
b0 ,
b1000010010110010101010001000101010111110101011100110011 4
b11011101 3
b100011 2
b0 %
b0 *
#490000
0#
#495000
b11011101 $
b11011101 )
b100011 "
b100011 (
b1 '
b1 +
1#
#500000
0#
#505000
b1000010010110010101010001000101010111110101001000110011 1
b11011101 /
b100011 .
b0 '
b0 +
1#
#510000
0#
#515000
b11011101 !
b11011101 ,
b1 %
b1 *
1#
#520000
0#
#525000
1#
#526000
b0 !
b0 ,
b1000010010110010101010001000101010111110100011001010111 1
b11011101110011001011101110101010 /
b100000 .
b11 0
b0 %
b0 *
#530000
0#
#535000
b11011101110011001011101110101010 !
b11011101110011001011101110101010 ,
b100000 "
b100000 (
b11 %
b11 *
1#
#540000
0#
#545000
1#
#546000
b0 !
b0 ,
b10011010100100101011000010111110101011101010111 4
b10010001101000101011001111000 3
b110000 2
b11 5
b0 %
b0 *
#550000
0#
#555000
b10010001101000101011001111000 $
b10010001101000101011001111000 )
b110000 "
b110000 (
b11 '
b11 +
1#
#560000
0#
#565000
b1001101010010010101100001011111010100100100001000110000 1
b1111000 /
b110000 .
b1 0
b0 '
b0 +
1#
#570000
0#
#575000
b1111000 !
b1111000 ,
b1 %
b1 *
1#
#580000
0#
#585000
1#
#586000
b0 !
b0 ,
b1001101010010010101100001011111010100100100001000110001 1
b1010110 /
b110001 .
b0 %
b0 *
#590000
0#
#595000
b1010110 !
b1010110 ,
b110001 "
b110001 (
b1 %
b1 *
1#
#600000
0#
#605000
1#
#606000
b0 !
b0 ,
b1001101010010010101100001011111010100100100001000110010 1
b110100 /
b110010 .
b0 %
b0 *
#610000
0#
#615000
b110100 !
b110100 ,
b110010 "
b110010 (
b1 %
b1 *
1#
#620000
0#
#625000
1#
#626000
b0 !
b0 ,
b1001101010010010101100001011111010100100100001000110011 1
b10010 /
b110011 .
b0 %
b0 *
#630000
0#
#635000
b10010 !
b10010 ,
b110011 "
b110011 (
b1 %
b1 *
1#
#640000
0#
#645000
1#
#646000
b0 !
b0 ,
b1001101010010010101100001011111010100100100100000110000 1
b101011001111000 /
b110000 .
b10 0
b0 %
b0 *
#650000
0#
#655000
b101011001111000 !
b101011001111000 ,
b110000 "
b110000 (
b10 %
b10 *
1#
#660000
0#
#665000
1#
#666000
b0 !
b0 ,
b1001101010010010101100001011111010100100100100000110001 1
b1001000110100 /
b110010 .
b0 %
b0 *
#670000
0#
#675000
b1001000110100 !
b1001000110100 ,
b110010 "
b110010 (
b10 %
b10 *
1#
#680000
0#
#685000
1#
#686000
b0 !
b0 ,
b100000000 -
1&
b0 %
b0 *
#690000
0#
#695000
1#
#700000
0#
#705000
b10100100101001101010100010111110101001000110001 1
b0 /
b0 .
b11 0
1#
#710000
0#
#715000
b100000000 -
b0 "
b0 (
b11 %
b11 *
1#
#720000
0#
#725000
1#
#726000
b100000000 -
b10100100101001101010100010111110101001000110010 1
b100 .
b0 %
b0 *
#730000
0#
#735000
b100000000 -
b100 "
b100 (
b11 %
b11 *
1#
#740000
0#
#745000
1#
#746000
0&
b0 %
b0 *
#750000
0#
#755000
1#
#760000
0#
#765000
b10000110100110001010010010111110101001000110001 1
b0 .
1#
#770000
0#
#775000
b0 "
b0 (
b11 %
b11 *
1#
#780000
0#
#785000
1#
#786000
b10000110100110001010010010111110101001000110010 1
b100 .
b0 %
b0 *
#790000
0#
#795000
b100 "
b100 (
b11 %
b11 *
1#
#800000
0#
#805000
1#
#806000
b1000101010001000100011101000101010111110101011100110001 4
b11111111111111111111111111111111 3
b111111111100 2
b0 %
b0 *
#810000
0#
#815000
b11111111111111111111111111111111 $
b11111111111111111111111111111111 )
b111111111100 "
b111111111100 (
b11 '
b11 +
1#
#820000
0#
#825000
b1000101010001000100011101000101010111110101001000110001 1
b11111111111111111111111111111111 /
b111111111100 .
b0 '
b0 +
1#
#830000
0#
#835000
b11111111111111111111111111111111 !
b11111111111111111111111111111111 ,
b11 %
b11 *
1#
#840000
0#
#845000
1#
#846000
b0 !
b0 ,
b0 %
b0 *
#850000
0#
#855000
b1000000 "
b1000000 (
1#
