src/ID_Stage/SIGN_EXTEND/sign_extend.v
`timescale 1ns/1ps

// Define a module called "SIGN_EXTEND"
module SIGN_EXTEND ( INST, IMM_SEL, IMM_EXT );

    input  wire [31:0] INST;
    input  wire [3:0]  IMM_SEL;
    output reg  [31:0] IMM_EXT;

    // Local type encoding 
    localparam U_TYPE = 3'b000;
    localparam J_TYPE = 3'b001;
    localparam I_TYPE = 3'b010;
    localparam B_TYPE = 3'b011;
    localparam S_TYPE = 3'b100;
    localparam SHAMT  = 3'b101;

    // Pre-decoded fields
    wire [19:0] u_field   = INST[31:12];
    wire [11:0] i_field   = INST[31:20];
    wire [11:0] s_field   = {INST[31:25], INST[11:7]};
    wire [4:0]  shamt_val = INST[24:20];

    always @(*) begin
        case (IMM_SEL[2:0])
            U_TYPE: begin
                // U-type (LUI/AUIPC): shift upper 20 bits left
                IMM_EXT = {u_field, 12'b0};
            end
            J_TYPE: begin
                if (IMM_SEL[3]) begin
                    // J-type (raw 20-bit as positive immediate)
                    IMM_EXT = {11'b0, u_field, 1'b0};
                end else begin
                    // J-type (real format): signed offset
                    IMM_EXT = {{12{INST[31]}}, INST[19:12], INST[20], INST[30:21], 1'b0};
                end
            end
            I_TYPE: begin
                if (IMM_SEL[3]) begin
                    // I-type unsigned (e.g., logical shift)
                    IMM_EXT = {20'b0, i_field};
                end else begin
                    // I-type signed (e.g., addi, lw)
                    IMM_EXT = {{20{i_field[11]}}, i_field};
                end
            end
            B_TYPE: begin
                // B-type branch: offset with sign-extension
                IMM_EXT = {{20{INST[31]}}, INST[7], INST[30:25], INST[11:8], 1'b0};
            end
            S_TYPE: begin
                if (IMM_SEL[3]) begin
                    // S-type unsigned (rare)
                    IMM_EXT = {20'b0, s_field};
                end else begin
                    // S-type signed (sw)
                    IMM_EXT = {{20{INST[31]}}, s_field};
                end
            end
            SHAMT: begin
                // Shift amount: zero-extended
                IMM_EXT = {27'b0, shamt_val};
            end
            default: begin
                // Fallback for safety
                IMM_EXT = 32'b0;
            end
        endcase
    end
endmodule

src/ID_Stage/SIGN_EXTEND/sign_extend_tb.v
`timescale 1ns/1ps

module sign_extend_tb;

    reg  [31:0] INST;
    reg  [3:0]  IMM_SEL;
    wire [31:0] IMM_EXT;

    // Connect DUT (Design Under Test)
    SIGN_EXTEND uut (
        .INST(INST),
        .IMM_SEL(IMM_SEL),
        .IMM_EXT(IMM_EXT)
    );

    // Type constants
    localparam U_TYPE = 4'b000;
    localparam J_TYPE = 4'b001;
    localparam I_TYPE = 4'b010;
    localparam B_TYPE = 4'b011;
    localparam S_TYPE = 4'b100;
    localparam SHAMT  = 4'b101;

    // Test result checker
    task check;
        input [31:0] expected;
        begin
            #1;
            if (IMM_EXT !== expected) begin
                $display("FAIL: INST=%h IMM_SEL=%b -> IMM_EXT=%h (expected %h)", INST, IMM_SEL, IMM_EXT, expected);
            end else begin
                $display("PASS: INST=%h IMM_SEL=%b -> IMM_EXT=%h", INST, IMM_SEL, IMM_EXT);
            end
        end
    endtask

    initial begin
        // U-type: LUI
        INST = 32'h12345000;
        IMM_SEL = U_TYPE;
        check(32'h12345000);

        // J-type signed offset
        INST = 32'b10000000010000000000000011011111;
        IMM_SEL = J_TYPE;
        check(32'hfff80400);  

        // I-type signed (-1)
        INST = 32'b11111111111100000000000000010011;
        IMM_SEL = I_TYPE;
        check(32'hffffffff);

        // I-type unsigned
        INST = 32'b00000000000100000000000000010011;
        IMM_SEL = I_TYPE | 4'b1000;  // IMM_SEL[3] = 1
        check(32'h00000001);

        // B-type signed offset
        INST = 32'b11111110000000000000000001100011;
        IMM_SEL = B_TYPE;
        check(32'hfffffe00);

        // S-type signed
        INST = 32'b11111110000000000010000000100011;
        IMM_SEL = S_TYPE;
        check(32'hffffffe0);

        // SHAMT
        INST = 32'b00000000000100000001000000010011;
        IMM_SEL = SHAMT;
        check(32'h00000001);

        // Default case
        INST = 32'h0;
        IMM_SEL = 4'b1111;
        check(32'h00000000);

        $display("All tests completed.");
        $finish;
    end

    // Dump waveform
    initial begin
        $dumpfile("sign_extend_tb.vcd");
        $dumpvars(0, sign_extend_tb);
    end

endmodule

src/ID_Stage/SIGN_EXTEND/sign_extend_tb.vcd
$date
	Thu Jul 10 14:29:40 2025
$end
$version
	Icarus Verilog
$end
$timescale
	1ps
$end
$scope module sign_extend_tb $end
$var wire 32 ! IMM_EXT [31:0] $end
$var parameter 4 " B_TYPE $end
$var parameter 4 # I_TYPE $end
$var parameter 4 $ J_TYPE $end
$var parameter 4 % SHAMT $end
$var parameter 4 & S_TYPE $end
$var parameter 4 ' U_TYPE $end
$var reg 4 ( IMM_SEL [3:0] $end
$var reg 32 ) INST [31:0] $end
$scope module uut $end
$var wire 4 * IMM_SEL [3:0] $end
$var wire 32 + INST [31:0] $end
$var wire 20 , u_field [19:0] $end
$var wire 5 - shamt_val [4:0] $end
$var wire 12 . s_field [11:0] $end
$var wire 12 / i_field [11:0] $end
$var parameter 4 0 B_TYPE $end
$var parameter 4 1 I_TYPE $end
$var parameter 4 2 J_TYPE $end
$var parameter 4 3 SHAMT $end
$var parameter 4 4 S_TYPE $end
$var parameter 4 5 U_TYPE $end
$var reg 32 6 IMM_EXT [31:0] $end
$upscope $end
$scope task check $end
$var reg 32 7 expected [31:0] $end
$upscope $end
$upscope $end
$enddefinitions $end
$comment Show the parameter values. $end
$dumpall
b0 5
b100 4
b101 3
b1 2
b10 1
b11 0
b0 '
b100 &
b101 %
b1 $
b10 #
b11 "
$end
#0
$dumpvars
b10010001101000101000000000000 7
b10010001101000101000000000000 6
b100100011 /
b100100000 .
b11 -
b10010001101000101 ,
b10010001101000101000000000000 +
b0 *
b10010001101000101000000000000 )
b0 (
b10010001101000101000000000000 !
$end
#1000
b11111111111100000000000000000100 !
b11111111111100000000000000000100 6
b10000000010000000000 ,
b100000000100 /
b100000000001 .
b100 -
b11111111111110000000010000000000 7
b1 (
b1 *
b10000000010000000000000011011111 )
b10000000010000000000000011011111 +
#2000
b11111111111111111111111111111111 !
b11111111111111111111111111111111 6
b11111111111100000000 ,
b111111111111 /
b111111100000 .
b11111 -
b11111111111111111111111111111111 7
b10 (
b10 *
b11111111111100000000000000010011 )
b11111111111100000000000000010011 +
#3000
b1 !
b1 6
b100000000 ,
b1 /
b0 .
b1 -
b1 7
b1010 (
b1010 *
b100000000000000010011 )
b100000000000000010011 +
#4000
b11111111111111111111011111100000 !
b11111111111111111111011111100000 6
b11111110000000000000 ,
b111111100000 /
b111111100000 .
b0 -
b11111111111111111111111000000000 7
b11 (
b11 *
b11111110000000000000000001100011 )
b11111110000000000000000001100011 +
#5000
b11111111111111111111111111100000 !
b11111111111111111111111111100000 6
b11111110000000000010 ,
b11111111111111111111111111100000 7
b100 (
b100 *
b11111110000000000010000000100011 )
b11111110000000000010000000100011 +
#6000
b1 !
b1 6
b100000001 ,
b1 /
b0 .
b1 -
b1 7
b101 (
b101 *
b100000001000000010011 )
b100000001000000010011 +
#7000
b0 !
b0 6
b0 ,
b0 /
b0 -
b0 7
b1111 (
b1111 *
b0 )
b0 +
