src/ID_Stage/HAZARD_UNIT/hazard_unit_corrected.v
`timescale 1ns/1ps

// Define a module called "HAZARD_UNIT"
module HAZARD_UNIT(
    ADDR1, ADDR2, EXRD, MEMRD, 
    EXWE, MEMWE, EXMEMR, 
    FDATA1SEL, FDATA2SEL, BUBBLE, STALL
);

    // Inputs
    input [4:0] ADDR1, ADDR2;    // Source register addresses (rs1, rs2)
    input [4:0] EXRD, MEMRD;     // Destination register addresses
    input EXWE, MEMWE;           // Write enable signals
    input EXMEMR;                // Memory read signal from EX stage
    
    // Outputs
    output reg [1:0] FDATA1SEL, FDATA2SEL;  // 2-bit forwarding select
    output reg BUBBLE, STALL;
    
    // Internal hazard detection signals
    wire ex_rs1_hazard, ex_rs2_hazard;      // EX stage hazards
    wire mem_rs1_hazard, mem_rs2_hazard;    // MEM stage hazards
    wire load_use_hazard;                   // Load-use hazard
    
    // EX stage hazard detection (ALU result forwarding)
    assign ex_rs1_hazard = EXWE && (EXRD != 5'b0) && (EXRD == ADDR1);
    assign ex_rs2_hazard = EXWE && (EXRD != 5'b0) && (EXRD == ADDR2);
    
    // MEM stage hazard detection (Memory/WB result forwarding)
    assign mem_rs1_hazard = MEMWE && (MEMRD != 5'b0) && (MEMRD == ADDR1);
    assign mem_rs2_hazard = MEMWE && (MEMRD != 5'b0) && (MEMRD == ADDR2);
    
    // Load-use hazard detection (requires stall)
    assign load_use_hazard = EXMEMR && (EXRD != 5'b0) && 
                            ((EXRD == ADDR1) || (EXRD == ADDR2));
    
    // Forwarding and stall logic
    always @(*) begin
        // Default values
        FDATA1SEL = 2'b00;  // No forwarding
        FDATA2SEL = 2'b00;  // No forwarding
        BUBBLE = 1'b0;
        STALL = 1'b0;
        
        // Check for load-use hazard first (highest priority)
        if (load_use_hazard) begin
            BUBBLE = 1'b1;
            STALL = 1'b1;
        end else begin
            // Forwarding logic (when no stall needed)
            
            // Source 1 forwarding
            if (ex_rs1_hazard && !EXMEMR) begin
                FDATA1SEL = 2'b01;  // Forward from EX/MEM pipeline register
            end else if (mem_rs1_hazard) begin
                FDATA1SEL = 2'b10;  // Forward from MEM/WB pipeline register
            end
            
            // Source 2 forwarding
            if (ex_rs2_hazard && !EXMEMR) begin
                FDATA2SEL = 2'b01;  // Forward from EX/MEM pipeline register
            end else if (mem_rs2_hazard) begin
                FDATA2SEL = 2'b10;  // Forward from MEM/WB pipeline register
            end
        end
    end

endmodule

src/ID_Stage/HAZARD_UNIT/hazard_unit_tb.v
`timescale 1ns/1ps

module hazard_unit_tb();
    // Testbench signals
    reg [4:0] ADDR1, ADDR2, EXRD, MEMRD;
    reg EXWE, MEMWE, EXMEMR;
    wire [1:0] FDATA1SEL, FDATA2SEL;
    wire BUBBLE, STALL;
    
    // Instantiate the hazard unit
    HAZARD_UNIT dut (
        .ADDR1(ADDR1), .ADDR2(ADDR2),
        .EXRD(EXRD), .MEMRD(MEMRD),
        .EXWE(EXWE), .MEMWE(MEMWE), .EXMEMR(EXMEMR),
        .FDATA1SEL(FDATA1SEL), .FDATA2SEL(FDATA2SEL),
        .BUBBLE(BUBBLE), .STALL(STALL)
    );
    
    // Task to test hazard scenarios
    task test_hazard;
        input [4:0] addr1, addr2, exrd, memrd;
        input exwe, memwe, exmemr;
        input [127:0] test_name;
        begin
            ADDR1 = addr1; ADDR2 = addr2;
            EXRD = exrd; MEMRD = memrd;
            EXWE = exwe; MEMWE = memwe; EXMEMR = exmemr;
            #10;
            $display("Test: %0s", test_name);
            $display("  Inputs: ADDR1=%d, ADDR2=%d, EXRD=%d, MEMRD=%d", addr1, addr2, exrd, memrd);
            $display("  Control: EXWE=%b, MEMWE=%b, EXMEMR=%b", exwe, memwe, exmemr);
            $display("  Output: FDATA1SEL=%b, FDATA2SEL=%b, BUBBLE=%b, STALL=%b", 
                     FDATA1SEL, FDATA2SEL, BUBBLE, STALL);
            $display("  Action: %s", 
                     BUBBLE ? "STALL PIPELINE" : 
                     (FDATA1SEL != 2'b00 || FDATA2SEL != 2'b00) ? "FORWARD DATA" : "NO HAZARD");
            $display("");
        end
    endtask
    
    initial begin
        $display("=== Hazard Unit Testbench ===");
        $display("Testing different hazard scenarios in RISC-V pipeline\n");
        
        // Test 1: No hazard
        test_hazard(5'd1, 5'd2, 5'd3, 5'd4, 1'b1, 1'b1, 1'b0, 
                   "No Hazard - Different registers");
        
        // Test 2: EX stage ALU forwarding (EX->ID)
        test_hazard(5'd3, 5'd2, 5'd3, 5'd4, 1'b1, 1'b1, 1'b0,
                   "EX Stage Forwarding - ADD x3,x1,x2; SUB x4,x3,x1");
        
        // Test 3: MEM stage forwarding (MEM->ID)
        test_hazard(5'd3, 5'd2, 5'd1, 5'd3, 1'b1, 1'b1, 1'b0,
                   "MEM Stage Forwarding - Previous instruction result");
        
        // Test 4: Load-use hazard (requires stall)
        test_hazard(5'd3, 5'd2, 5'd3, 5'd4, 1'b1, 1'b1, 1'b1,
                   "Load-Use Hazard - LW x3,0(x1); ADD x4,x3,x2");
        
        // Test 5: Both operands need forwarding
        test_hazard(5'd3, 5'd4, 5'd3, 5'd4, 1'b1, 1'b1, 1'b0,
                   "Both Operands Forward - EX:x3, MEM:x4");
        
        // Test 6: Register x0 (should not forward)
        test_hazard(5'd0, 5'd2, 5'd0, 5'd4, 1'b1, 1'b1, 1'b0,
                   "Register x0 Test - Should not forward");
        
        // Test 7: Multiple hazards with priority
        test_hazard(5'd3, 5'd3, 5'd3, 5'd3, 1'b1, 1'b1, 1'b1,
                   "Load-Use with Multiple Conflicts");
        
        // Test 8: Write enable disabled
        test_hazard(5'd3, 5'd2, 5'd3, 5'd4, 1'b0, 1'b0, 1'b0,
                   "Write Disabled - No hazard even with matching registers");
        
        $display("=== Hazard Unit Test Complete ===");
        $finish;
    end
    
    // Generate VCD file
    initial begin
        $dumpfile("hazard_unit_tb.vcd");
        $dumpvars(0, hazard_unit_tb);
    end
    
endmodule

src/ID_Stage/HAZARD_UNIT/hazard_unit_tb.vcd
$date
	Fri Jul 11 10:03:34 2025
$end
$version
	Icarus Verilog
$end
$timescale
	1ps
$end
$scope module hazard_unit_tb $end
$var wire 1 ! STALL $end
$var wire 2 " FDATA2SEL [1:0] $end
$var wire 2 # FDATA1SEL [1:0] $end
$var wire 1 $ BUBBLE $end
$var reg 5 % ADDR1 [4:0] $end
$var reg 5 & ADDR2 [4:0] $end
$var reg 1 ' EXMEMR $end
$var reg 5 ( EXRD [4:0] $end
$var reg 1 ) EXWE $end
$var reg 5 * MEMRD [4:0] $end
$var reg 1 + MEMWE $end
$scope module dut $end
$var wire 5 , ADDR1 [4:0] $end
$var wire 5 - ADDR2 [4:0] $end
$var wire 1 ' EXMEMR $end
$var wire 5 . EXRD [4:0] $end
$var wire 1 ) EXWE $end
$var wire 5 / MEMRD [4:0] $end
$var wire 1 + MEMWE $end
$var wire 1 0 ex_rs1_hazard $end
$var wire 1 1 ex_rs2_hazard $end
$var wire 1 2 load_use_hazard $end
$var wire 1 3 mem_rs1_hazard $end
$var wire 1 4 mem_rs2_hazard $end
$var reg 1 $ BUBBLE $end
$var reg 2 5 FDATA1SEL [1:0] $end
$var reg 2 6 FDATA2SEL [1:0] $end
$var reg 1 ! STALL $end
$upscope $end
$scope task test_hazard $end
$var reg 5 7 addr1 [4:0] $end
$var reg 5 8 addr2 [4:0] $end
$var reg 1 9 exmemr $end
$var reg 5 : exrd [4:0] $end
$var reg 1 ; exwe $end
$var reg 5 < memrd [4:0] $end
$var reg 1 = memwe $end
$var reg 128 > test_name [127:0] $end
$upscope $end
$upscope $end
$enddefinitions $end
$comment Show the parameter values. $end
$dumpall
$end
#0
$dumpvars
b1100110011001010111001001100101011011100111010000100000011100100110010101100111011010010111001101110100011001010111001001110011 >
1=
b100 <
1;
b11 :
09
b10 8
b1 7
b0 6
b0 5
04
03
02
01
00
b100 /
b11 .
b10 -
b1 ,
1+
b100 *
1)
b11 (
0'
b10 &
b1 %
0$
b0 #
b0 "
0!
$end
#10000
b1 #
b1 5
10
b11 %
b11 ,
b1111000001100100011101100100000010100110101010101000010001000000111100000110100001011000111100000110011001011000111100000110001 >
b11 7
#20000
b10 #
b10 5
13
00
b11 *
b11 /
b1 (
b1 .
b1110011011101000111001001110101011000110111010001101001011011110110111000100000011100100110010101110011011101010110110001110100 >
b11 <
b1 :
#30000
1!
1$
12
b0 #
b0 5
03
10
1'
b100 *
b100 /
b11 (
b11 .
b110001001010010011101100100000010000010100010001000100001000000111100000110100001011000111100000110011001011000111100000110010 >
19
b100 <
b11 :
#40000
b10 "
b10 6
b1 #
b1 5
02
0!
0$
14
0'
b100 &
b100 -
b100000001011010010000001000101010110000011101001111000001100110010110000100000010011010100010101001101001110100111100000110100 >
09
b100 8
#50000
00
b0 "
b0 6
b0 #
b0 5
04
b0 (
b0 .
b10 &
b10 -
b0 %
b0 ,
b1101111011101010110110001100100001000000110111001101111011101000010000001100110011011110111001001110111011000010111001001100100 >
b0 :
b10 8
b0 7
#60000
1!
1$
10
11
12
b0 "
b0 6
b0 #
b0 5
13
14
1'
b11 *
b11 /
b11 (
b11 .
b11 &
b11 -
b11 %
b11 ,
b1101100011101000110100101110000011011000110010100100000010000110110111101101110011001100110110001101001011000110111010001110011 >
19
b11 <
b11 :
b11 8
b11 7
#70000
02
00
0!
0$
03
01
04
0'
0+
0)
b100 *
b100 /
b10 &
b10 -
b1110100011000110110100001101001011011100110011100100000011100100110010101100111011010010111001101110100011001010111001001110011 >
09
0=
0;
b100 <
b10 8
