src/EX_Stage/BRANCH_SELECTOR/branch_selector.v
`timescale 1ns/1ps

// Define a module called "BRANCH_SELECTOR"
module BRANCH_SELECTOR(DATA1, DATA2, BRANCH_TYPE, BRANCH_TAKEN);

    // Inputs and Outputs
    input [31:0] DATA1;        // First operand (rs1)
    input [31:0] DATA2;         // Second operand (rs2)
    input [2:0] BRANCH_TYPE;    // Branch type selector
    output BRANCH_TAKEN;        // Branch decision output

    // Branch type encoding (RISC-V standard)
    localparam BEQ  = 3'b000;   // Branch if equal
    localparam BNE  = 3'b001;   // Branch if not equal
    localparam BLT  = 3'b100;   // Branch if less than (signed)
    localparam BGE  = 3'b101;   // Branch if greater or equal (signed)
    localparam BLTU = 3'b110;   // Branch if less than (unsigned)
    localparam BGEU = 3'b111;   // Branch if greater or equal (unsigned)

    // Internal comparison signals
    wire EQUAL;
    wire SIGNED_LT;
    wire UNSIGNED_LT;

    // Comparison operations
    assign EQUAL = (DATA1 == DATA2);
    assign SIGNED_LT = ($signed(DATA1) < $signed(DATA2));
    assign UNSIGNED_LT = (DATA1 < DATA2);

    // Branch decision logic
    reg branch_decision;
    
    always @(*) begin
        case (BRANCH_TYPE)
            BEQ:  branch_decision = EQUAL;              // Branch if equal
            BNE:  branch_decision = ~EQUAL;             // Branch if not equal
            BLT:  branch_decision = SIGNED_LT;          // Branch if less than (signed)
            BGE:  branch_decision = ~SIGNED_LT;         // Branch if greater or equal (signed)
            BLTU: branch_decision = UNSIGNED_LT;        // Branch if less than (unsigned)
            BGEU: branch_decision = ~UNSIGNED_LT;       // Branch if greater or equal (unsigned)
            default: branch_decision = 1'b0;            // No branch for undefined types
        endcase
    end

    assign BRANCH_TAKEN = branch_decision;

endmodule

src/EX_Stage/BRANCH_SELECTOR/branch_selector_tb.v
`timescale 1ns/1ps

module branch_selector_tb();
    // Testbench signals
    reg [31:0] DATA1, DATA2;
    reg [2:0] BRANCH_TYPE;
    wire BRANCH_TAKEN;
    
    // Instantiate the branch selector
    BRANCH_SELECTOR dut (
        .DATA1(DATA1),
        .DATA2(DATA2),
        .BRANCH_TYPE(BRANCH_TYPE),
        .BRANCH_TAKEN(BRANCH_TAKEN)
    );
    
    // Task to test branch operations
    task test_branch;
        input [2:0] branch_type;
        input [31:0] data1, data2;
        input expected;
        input [31:0] test_name; // 4 characters
        begin
            DATA1 = data1;
            DATA2 = data2;
            BRANCH_TYPE = branch_type;
            #10;
            $display("Time: %0t | Test: %0s | DATA1: %h | DATA2: %h | Type: %b | BRANCH_TAKEN: %b | Expected: %b | %s", 
                     $time, test_name, data1, data2, branch_type, BRANCH_TAKEN, expected, 
                     (BRANCH_TAKEN == expected) ? "PASS" : "FAIL");
        end
    endtask
    
    initial begin
        $display("=== Branch Selector Testbench Started ===");
        $display("Time | Test | DATA1    | DATA2    | Type | BRANCH | Expected | Result");
        $display("-----|------|----------|----------|------|--------|----------|-------");
        
        // Initialize
        DATA1 = 0;
        DATA2 = 0;
        BRANCH_TYPE = 0;
        #5;
        
        // Test BEQ (Branch if Equal) - Type 000
        test_branch(3'b000, 32'h12345678, 32'h12345678, 1'b1, "BEQ1"); // Equal values
        test_branch(3'b000, 32'h12345678, 32'h87654321, 1'b0, "BEQ2"); // Different values
        test_branch(3'b000, 32'h00000000, 32'h00000000, 1'b1, "BEQ3"); // Zero values
        
        // Test BNE (Branch if Not Equal) - Type 001
        test_branch(3'b001, 32'h12345678, 32'h87654321, 1'b1, "BNE1"); // Different values
        test_branch(3'b001, 32'h12345678, 32'h12345678, 1'b0, "BNE2"); // Equal values
        test_branch(3'b001, 32'hFFFFFFFF, 32'h00000000, 1'b1, "BNE3"); // Max vs Min
        
        // Test BLT (Branch if Less Than - Signed) - Type 100
        test_branch(3'b100, 32'h00000010, 32'h00000020, 1'b1, "BLT1"); // 16 < 20 (both positive)
        test_branch(3'b100, 32'h00000020, 32'h00000010, 1'b0, "BLT2"); // 20 > 16 (both positive)
        test_branch(3'b100, 32'hFFFFFFF0, 32'h00000010, 1'b1, "BLT3"); // -16 < 16 (negative vs positive)
        test_branch(3'b100, 32'h00000010, 32'hFFFFFFF0, 1'b0, "BLT4"); // 16 > -16 (positive vs negative)
        test_branch(3'b100, 32'hFFFFFFE0, 32'hFFFFFFF0, 1'b1, "BLT5"); // -32 < -16 (both negative)
        test_branch(3'b100, 32'h12345678, 32'h12345678, 1'b0, "BLT6"); // Equal values
        
        // Test BGE (Branch if Greater or Equal - Signed) - Type 101
        test_branch(3'b101, 32'h00000020, 32'h00000010, 1'b1, "BGE1"); // 20 >= 16
        test_branch(3'b101, 32'h00000010, 32'h00000010, 1'b1, "BGE2"); // 16 >= 16 (equal)
        test_branch(3'b101, 32'h00000010, 32'h00000020, 1'b0, "BGE3"); // 16 < 20
        test_branch(3'b101, 32'h00000010, 32'hFFFFFFF0, 1'b1, "BGE4"); // 16 >= -16
        test_branch(3'b101, 32'hFFFFFFF0, 32'hFFFFFFE0, 1'b1, "BGE5"); // -16 >= -32
        
        // Test BLTU (Branch if Less Than - Unsigned) - Type 110
        test_branch(3'b110, 32'h00000010, 32'h00000020, 1'b1, "BLTU1"); // 16 < 20 (unsigned)
        test_branch(3'b110, 32'h00000020, 32'h00000010, 1'b0, "BLTU2"); // 20 > 16 (unsigned)
        test_branch(3'b110, 32'h00000010, 32'hFFFFFFF0, 1'b1, "BLTU3"); // 16 < 4294967280 (unsigned)
        test_branch(3'b110, 32'hFFFFFFF0, 32'h00000010, 1'b0, "BLTU4"); // 4294967280 > 16 (unsigned)
        test_branch(3'b110, 32'h12345678, 32'h12345678, 1'b0, "BLTU5"); // Equal values
        
        // Test BGEU (Branch if Greater or Equal - Unsigned) - Type 111
        test_branch(3'b111, 32'h00000020, 32'h00000010, 1'b1, "BGEU1"); // 20 >= 16 (unsigned)
        test_branch(3'b111, 32'h00000010, 32'h00000010, 1'b1, "BGEU2"); // 16 >= 16 (equal)
        test_branch(3'b111, 32'h00000010, 32'h00000020, 1'b0, "BGEU3"); // 16 < 20 (unsigned)
        test_branch(3'b111, 32'hFFFFFFF0, 32'h00000010, 1'b1, "BGEU4"); // 4294967280 >= 16 (unsigned)
        test_branch(3'b111, 32'h00000010, 32'hFFFFFFF0, 1'b0, "BGEU5"); // 16 < 4294967280 (unsigned)
        
        // Test undefined branch type (should not branch)
        test_branch(3'b010, 32'h12345678, 32'h87654321, 1'b0, "UND1"); // Undefined type
        test_branch(3'b011, 32'h00000010, 32'h00000020, 1'b0, "UND2"); // Undefined type
        
        // Edge case tests
        $display("\n=== Edge Case Tests ===");
        test_branch(3'b000, 32'hFFFFFFFF, 32'hFFFFFFFF, 1'b1, "EDG1"); // BEQ with all 1s
        test_branch(3'b100, 32'h80000000, 32'h7FFFFFFF, 1'b1, "EDG2"); // BLT: most negative < most positive
        test_branch(3'b110, 32'h80000000, 32'h7FFFFFFF, 1'b0, "EDG3"); // BLTU: most negative > most positive (unsigned)
        
        $display("\n=== Branch Selector Testbench Completed ===");
        $finish;
    end
    
    // Generate VCD file for waveform viewing
    initial begin
        $dumpfile("branch_selector_tb.vcd");
        $dumpvars(0, branch_selector_tb);
    end
    
endmodule

src/EX_Stage/BRANCH_SELECTOR/branch_selector_tb.vcd
$date
	Thu Jul 10 21:50:46 2025
$end
$version
	Icarus Verilog
$end
$timescale
	1ps
$end
$scope module branch_selector_tb $end
$var wire 1 ! BRANCH_TAKEN $end
$var reg 3 " BRANCH_TYPE [2:0] $end
$var reg 32 # DATA1 [31:0] $end
$var reg 32 $ DATA2 [31:0] $end
$scope module dut $end
$var wire 1 ! BRANCH_TAKEN $end
$var wire 3 % BRANCH_TYPE [2:0] $end
$var wire 32 & DATA1 [31:0] $end
$var wire 32 ' DATA2 [31:0] $end
$var wire 1 ( UNSIGNED_LT $end
$var wire 1 ) SIGNED_LT $end
$var wire 1 * EQUAL $end
$var parameter 3 + BEQ $end
$var parameter 3 , BGE $end
$var parameter 3 - BGEU $end
$var parameter 3 . BLT $end
$var parameter 3 / BLTU $end
$var parameter 3 0 BNE $end
$var reg 1 1 branch_decision $end
$upscope $end
$scope task test_branch $end
$var reg 3 2 branch_type [2:0] $end
$var reg 32 3 data1 [31:0] $end
$var reg 32 4 data2 [31:0] $end
$var reg 1 5 expected $end
$var reg 32 6 test_name [31:0] $end
$upscope $end
$upscope $end
$enddefinitions $end
$comment Show the parameter values. $end
$dumpall
b1 0
b110 /
b100 .
b111 -
b101 ,
b0 +
$end
#0
$dumpvars
bx 6
x5
bx 4
bx 3
bx 2
11
1*
0)
0(
b0 '
b0 &
b0 %
b0 $
b0 #
b0 "
1!
$end
#5000
b10010001101000101011001111000 $
b10010001101000101011001111000 '
1*
b10010001101000101011001111000 #
b10010001101000101011001111000 &
b1000010010001010101000100110001 6
15
b10010001101000101011001111000 4
b10010001101000101011001111000 3
b0 2
#15000
0!
01
0*
1(
b10000111011001010100001100100001 $
b10000111011001010100001100100001 '
b1000010010001010101000100110010 6
05
b10000111011001010100001100100001 4
#25000
1!
11
1*
0(
b0 $
b0 '
b0 #
b0 &
b1000010010001010101000100110011 6
15
b0 4
b0 3
#35000
b1 "
b1 %
1(
b10000111011001010100001100100001 $
b10000111011001010100001100100001 '
0*
b10010001101000101011001111000 #
b10010001101000101011001111000 &
b1000010010011100100010100110001 6
b10000111011001010100001100100001 4
b10010001101000101011001111000 3
b1 2
#45000
0!
01
1*
0(
b10010001101000101011001111000 $
b10010001101000101011001111000 '
b1000010010011100100010100110010 6
05
b10010001101000101011001111000 4
#55000
1!
11
b0 $
b0 '
0*
1)
b11111111111111111111111111111111 #
b11111111111111111111111111111111 &
b1000010010011100100010100110011 6
15
b0 4
b11111111111111111111111111111111 3
#65000
b100 "
b100 %
1(
b100000 $
b100000 '
1)
b10000 #
b10000 &
b1000010010011000101010000110001 6
b100000 4
b10000 3
b100 2
#75000
0!
01
b10000 $
b10000 '
0*
0)
0(
b100000 #
b100000 &
b1000010010011000101010000110010 6
05
b10000 4
b100000 3
#85000
1!
11
1)
b11111111111111111111111111110000 #
b11111111111111111111111111110000 &
b1000010010011000101010000110011 6
15
b11111111111111111111111111110000 3
#95000
0!
01
1(
b11111111111111111111111111110000 $
b11111111111111111111111111110000 '
0*
0)
b10000 #
b10000 &
b1000010010011000101010000110100 6
05
b11111111111111111111111111110000 4
b10000 3
#105000
1!
11
1)
b11111111111111111111111111100000 #
b11111111111111111111111111100000 &
b1000010010011000101010000110101 6
15
b11111111111111111111111111100000 3
#115000
0!
01
1*
0(
b10010001101000101011001111000 $
b10010001101000101011001111000 '
0)
b10010001101000101011001111000 #
b10010001101000101011001111000 &
b1000010010011000101010000110110 6
05
b10010001101000101011001111000 4
b10010001101000101011001111000 3
#125000
1!
11
b101 "
b101 %
b10000 $
b10000 '
0*
0)
0(
b100000 #
b100000 &
b1000010010001110100010100110001 6
15
b10000 4
b100000 3
b101 2
#135000
1*
b10000 #
b10000 &
b1000010010001110100010100110010 6
b10000 3
#145000
0!
01
0*
1)
1(
b100000 $
b100000 '
b1000010010001110100010100110011 6
05
b100000 4
#155000
1!
11
0)
b11111111111111111111111111110000 $
b11111111111111111111111111110000 '
b1000010010001110100010100110100 6
15
b11111111111111111111111111110000 4
#165000
b11111111111111111111111111100000 $
b11111111111111111111111111100000 '
0*
0(
b11111111111111111111111111110000 #
b11111111111111111111111111110000 &
b1000010010001110100010100110101 6
b11111111111111111111111111100000 4
b11111111111111111111111111110000 3
#175000
b110 "
b110 %
1)
b100000 $
b100000 '
1(
b10000 #
b10000 &
b1001100010101000101010100110001 6
b100000 4
b10000 3
b110 2
#185000
0!
01
b10000 $
b10000 '
0*
0)
0(
b100000 #
b100000 &
b1001100010101000101010100110010 6
05
b10000 4
b100000 3
#195000
1!
11
1(
b11111111111111111111111111110000 $
b11111111111111111111111111110000 '
0*
b10000 #
b10000 &
b1001100010101000101010100110011 6
15
b11111111111111111111111111110000 4
b10000 3
#205000
0!
01
1)
b10000 $
b10000 '
0*
0(
b11111111111111111111111111110000 #
b11111111111111111111111111110000 &
b1001100010101000101010100110100 6
05
b10000 4
b11111111111111111111111111110000 3
#215000
1*
b10010001101000101011001111000 $
b10010001101000101011001111000 '
0)
b10010001101000101011001111000 #
b10010001101000101011001111000 &
b1001100010101000101010100110101 6
b10010001101000101011001111000 4
b10010001101000101011001111000 3
#225000
1!
11
b111 "
b111 %
b10000 $
b10000 '
0*
0)
0(
b100000 #
b100000 &
b1000111010001010101010100110001 6
15
b10000 4
b100000 3
b111 2
#235000
1*
b10000 #
b10000 &
b1000111010001010101010100110010 6
b10000 3
#245000
0!
01
0*
1)
1(
b100000 $
b100000 '
b1000111010001010101010100110011 6
05
b100000 4
#255000
1!
11
b10000 $
b10000 '
0(
b11111111111111111111111111110000 #
b11111111111111111111111111110000 &
b1000111010001010101010100110100 6
15
b10000 4
b11111111111111111111111111110000 3
#265000
0!
01
1(
b11111111111111111111111111110000 $
b11111111111111111111111111110000 '
0*
0)
b10000 #
b10000 &
b1000111010001010101010100110101 6
05
b11111111111111111111111111110000 4
b10000 3
#275000
b10 "
b10 %
b10000111011001010100001100100001 $
b10000111011001010100001100100001 '
b10010001101000101011001111000 #
b10010001101000101011001111000 &
b1010101010011100100010000110001 6
b10000111011001010100001100100001 4
b10010001101000101011001111000 3
b10 2
#285000
b11 "
b11 %
1)
b100000 $
b100000 '
b10000 #
b10000 &
b1010101010011100100010000110010 6
b100000 4
b10000 3
b11 2
#295000
1!
11
b0 "
b0 %
1*
0)
b11111111111111111111111111111111 $
b11111111111111111111111111111111 '
0(
b11111111111111111111111111111111 #
b11111111111111111111111111111111 &
b1000101010001000100011100110001 6
15
b11111111111111111111111111111111 4
b11111111111111111111111111111111 3
b0 2
#305000
b100 "
b100 %
b1111111111111111111111111111111 $
b1111111111111111111111111111111 '
0*
1)
0(
b10000000000000000000000000000000 #
b10000000000000000000000000000000 &
b1000101010001000100011100110010 6
b1111111111111111111111111111111 4
b10000000000000000000000000000000 3
b100 2
#315000
0!
01
b110 "
b110 %
b1000101010001000100011100110011 6
05
b110 2
