src/ID_Stage/REG_FILE/reg_file.v
`timescale 1ns/1ps

// Define a module called "REG_FILE"
module REG_FILE(IN,OUT1,OUT2,ADDR1,ADDR2,ADDRW,WRITE,CLK,RESET); 

	// Declare inputs and outputs of the module
	input [4:0] ADDR1,ADDR2,ADDRW;
	input [31:0] IN;
    input WRITE,CLK,RESET;
	output [31:0] OUT1,OUT2;

	/*REGISTERARRAY[x]->xth Array of a 8 registers (8bit memory location)
	Therefore channging the value x can acces 8bit memoary 
	for store data or load the data in that location*/
    reg [31:0] REGISTERARRAY[31:0];//make a 8x8 register array
	 
    integer bit;//for to use to increment in for loop
    assign #2 OUT1 = REGISTERARRAY[ADDR1]; //data in location out1address value assign to out1
	assign #2 OUT2 = REGISTERARRAY[ADDR2]; //data in location out2address value assign to out2
	
    //checking signal when positive clock edge and repond to write and read signals
	always @(posedge CLK) 
	begin
		//when write signal is high
		if (WRITE == 1'b1 && ADDRW !=5'd0) begin 
			#1 REGISTERARRAY[ADDRW] <= IN;//store the in value to suitable register
		end
		//when Reset signal high
		else if(RESET == 1) begin 
			#1 for(bit = 0 ; bit < 32 ; bit = bit + 1) begin 
				//all register values turn to 0
				REGISTERARRAY[bit] <= 32'd0;
			end //end for loop
		end	
	end
endmodule

src/ID_Stage/REG_FILE/reg_file_tb.v
`timescale 1ns/1ps

module reg_file_tb;

    // Inputs
    reg [31:0] IN;
    reg [4:0] ADDR1, ADDR2, ADDRW;
    reg WRITE, CLK, RESET;

    // Outputs
    wire [31:0] OUT1, OUT2;

    // Instantiate the reg_file module
    REG_FILE uut (
        .IN(IN),
        .OUT1(OUT1),
        .OUT2(OUT2),
        .ADDR1(ADDR1),
        .ADDR2(ADDR2),
        .ADDRW(ADDRW),
        .WRITE(WRITE),
        .CLK(CLK),
        .RESET(RESET)
    );

    // Clock generator: Toggle every 5ns
    always #5 CLK = ~CLK;

    initial begin
        // Initial values
        CLK = 0;
        RESET = 0;
        WRITE = 0;
        IN = 0;
        ADDR1 = 0;
        ADDR2 = 0;
        ADDRW = 0;

        // Start of simulation
        $display("Time\tWRITE\tADDRW\tIN\tADDR1\tADDR2\tOUT1\tOUT2");

        // Reset the register file
        RESET = 1;
        #10;
        RESET = 0;

        // Write 42 to register x5
        IN = 32'd42;
        ADDRW = 5'd5;
        WRITE = 1;
        #10;

        // Write 99 to register x10
        IN = 32'd99;
        ADDRW = 5'd10;
        #10;

        // Disable write
        WRITE = 0;

        // Read from registers x5 and x10
        ADDR1 = 5'd5;
        ADDR2 = 5'd10;
        #10;

        $display("%0t\t%b\t%0d\t%0d\t%0d\t%0d\t%0d\t%0d",
                 $time, WRITE, ADDRW, IN, ADDR1, ADDR2, OUT1, OUT2);

        // Registers with no writes, should be 0
        ADDR1 = 5'd0;
        ADDR2 = 5'd1;
        #10;

        $display("%0t\t%b\t%0d\t%0d\t%0d\t%0d\t%0d\t%0d",
                 $time, WRITE, ADDRW, IN, ADDR1, ADDR2, OUT1, OUT2);

        $finish;
    end

    // Dump waveform
    initial begin
        $dumpfile("reg_file_tb.vcd");
        $dumpvars(0, reg_file_tb);
    end

endmodule

src/ID_Stage/REG_FILE/reg_file_tb.vcd
$date
	Thu Jul 10 14:45:53 2025
$end
$version
	Icarus Verilog
$end
$timescale
	1ps
$end
$scope module reg_file_tb $end
$var wire 32 ! OUT2 [31:0] $end
$var wire 32 " OUT1 [31:0] $end
$var reg 5 # ADDR1 [4:0] $end
$var reg 5 $ ADDR2 [4:0] $end
$var reg 5 % ADDRW [4:0] $end
$var reg 1 & CLK $end
$var reg 32 ' IN [31:0] $end
$var reg 1 ( RESET $end
$var reg 1 ) WRITE $end
$scope module uut $end
$var wire 5 * ADDR1 [4:0] $end
$var wire 5 + ADDR2 [4:0] $end
$var wire 5 , ADDRW [4:0] $end
$var wire 1 & CLK $end
$var wire 32 - IN [31:0] $end
$var wire 32 . OUT1 [31:0] $end
$var wire 32 / OUT2 [31:0] $end
$var wire 1 ( RESET $end
$var wire 1 ) WRITE $end
$var integer 32 0 bit [31:0] $end
$upscope $end
$upscope $end
$scope module reg_file_tb $end
$scope module uut $end
$upscope $end
$upscope $end
$enddefinitions $end
$comment Show the parameter values. $end
$dumpall
$end
#0
$dumpvars
bx 0
bx /
bx .
b0 -
b0 ,
b0 +
b0 *
0)
1(
b0 '
0&
b0 %
b0 $
b0 #
bx "
bx !
$end
#5000
1&
#6000
b100000 0
#8000
b0 "
b0 .
b0 !
b0 /
#10000
0&
1)
b101 %
b101 ,
b101010 '
b101010 -
0(
#15000
1&
#20000
0&
b1010 %
b1010 ,
b1100011 '
b1100011 -
#25000
1&
#30000
0&
b1010 $
b1010 +
b101 #
b101 *
0)
#32000
b1100011 !
b1100011 /
b101010 "
b101010 .
#35000
1&
#40000
0&
b1 $
b1 +
b0 #
b0 *
#42000
b0 !
b0 /
b0 "
b0 .
